{
  "season_id": 2,
  "dungeon_id": 12915,
  "dungeon_name": "Nexus-Point Xenas",
  "class_name": "Druid",
  "spec_name": "Restoration",
  "sample_count": 100,
  "dps": {
    "avg": 16955.6,
    "median": 13833.9,
    "p25": 11189.9,
    "p75": 17333.8,
    "max": 162733.9,
    "min": 2900.6,
    "sample_count": 100
  },
  "clear_time": {
    "avg": 1739502.7,
    "median": 1740339.0,
    "p25": 1691087.5,
    "p75": 1776048.5
  },
  "keystone": {
    "avg": 21.1,
    "max": 22,
    "min": 21
  },
  "score": {
    "avg": 486.3,
    "median": 501.3,
    "p25": 500.5,
    "p75": 502.6,
    "max": 518.1,
    "min": 313.8,
    "sample_count": 100
  },
  "talents": [
    {
      "build": "d41d8cd98f00",
      "count": 8,
      "pct": 8.0,
      "avg_dps": 30083.3
    },
    {
      "build": "12c4b88437d7",
      "count": 5,
      "pct": 5.0,
      "avg_dps": 13853.6
    },
    {
      "build": "8043ea7d8e51",
      "count": 3,
      "pct": 3.0,
      "avg_dps": 9039.0
    },
    {
      "build": "7129b8dcef4f",
      "count": 2,
      "pct": 2.0,
      "avg_dps": 23734.6
    },
    {
      "build": "3a8a7f78e906",
      "count": 2,
      "pct": 2.0,
      "avg_dps": 18666.1
    },
    {
      "build": "d4c36edb6ccb",
      "count": 2,
      "pct": 2.0,
      "avg_dps": 16582.9
    },
    {
      "build": "f7dc9d03da49",
      "count": 2,
      "pct": 2.0,
      "avg_dps": 16666.4
    },
    {
      "build": "af856848004b",
      "count": 2,
      "pct": 2.0,
      "avg_dps": 18298.8
    },
    {
      "build": "2aacdfd30881",
      "count": 2,
      "pct": 2.0,
      "avg_dps": 13301.7
    },
    {
      "build": "caa894b17cd7",
      "count": 2,
      "pct": 2.0,
      "avg_dps": 17640.6
    },
    {
      "build": "7fff8e13910c",
      "count": 2,
      "pct": 2.0,
      "avg_dps": 14817.1
    },
    {
      "build": "4c71e1083a24",
      "count": 2,
      "pct": 2.0,
      "avg_dps": 10784.3
    },
    {
      "build": "ce1cb1df5db5",
      "count": 2,
      "pct": 2.0,
      "avg_dps": 8139.4
    },
    {
      "build": "11dc791385ce",
      "count": 1,
      "pct": 1.0,
      "avg_dps": 14933.0
    },
    {
      "build": "9095af8009c0",
      "count": 1,
      "pct": 1.0,
      "avg_dps": 14635.7
    },
    {
      "build": "bc0bb8ffb883",
      "count": 1,
      "pct": 1.0,
      "avg_dps": 10100.5
    },
    {
      "build": "36378fe15ab9",
      "count": 1,
      "pct": 1.0,
      "avg_dps": 61244.9
    },
    {
      "build": "7c21a4566794",
      "count": 1,
      "pct": 1.0,
      "avg_dps": 42481.1
    },
    {
      "build": "e50c0eb470c6",
      "count": 1,
      "pct": 1.0,
      "avg_dps": 39208.9
    },
    {
      "build": "ee4518e4e3c6",
      "count": 1,
      "pct": 1.0,
      "avg_dps": 36180.1
    }
  ],
  "gear": {
    "head": [
      {
        "itemID": 250024,
        "name": "Branches of the Luminous Bloom",
        "icon": "inv_helm_leather_raiddruidmidnight_d_01",
        "count": 92,
        "pct": 92.0,
        "avg_itemLevel": 286.7
      }
    ],
    "neck": [
      {
        "itemID": 151309,
        "name": "Necklace of the Twisting Void",
        "icon": "inv_7_0raid_necklace_06d",
        "count": 27,
        "pct": 27.0,
        "avg_itemLevel": 278.9
      },
      {
        "itemID": 251096,
        "name": "Pendant of Aching Grief",
        "icon": "inv_12_jewelry_silvermoonelf_necklace_white",
        "count": 26,
        "pct": 26.0,
        "avg_itemLevel": 277.8
      },
      {
        "itemID": 249368,
        "name": "Eternal Voidsong Chain",
        "icon": "inv_12_jewelry_silvermoonelf_necklace_blue1",
        "count": 18,
        "pct": 18.0,
        "avg_itemLevel": 286.1
      },
      {
        "itemID": 266314,
        "name": "Novice Combatant's Necklace",
        "icon": "inv_112_raidtrinkets_necklace01_etherealnontechnologicalstyle_terra",
        "count": 9,
        "pct": 9.0,
        "avg_itemLevel": 276.0
      },
      {
        "itemID": 240950,
        "name": "Masterwork Sin'dorei Amulet",
        "icon": "inv_12_profession_jewelcrafting_necklace2_gold",
        "count": 8,
        "pct": 8.0,
        "avg_itemLevel": 285.0
      },
      {
        "itemID": 250247,
        "name": "Amulet of the Abyssal Hymn",
        "icon": "inv_12_jewelry_devouringhost_necklace_bronze2",
        "count": 4,
        "pct": 4.0,
        "avg_itemLevel": 279.2
      }
    ],
    "shoulder": [
      {
        "itemID": 250022,
        "name": "Seedpods of the Luminous Bloom",
        "icon": "inv_shoulder_leather_raiddruidmidnight_d_01",
        "count": 88,
        "pct": 88.0,
        "avg_itemLevel": 284.7
      },
      {
        "itemID": 251092,
        "name": "Fallen Grunt's Mantle",
        "icon": "inv_shoulder_leather_dungeonharronir_c_01",
        "count": 1,
        "pct": 1.0,
        "avg_itemLevel": 276.0
      },
      {
        "itemID": 244572,
        "name": "Silvermoon Agent's Mantle",
        "icon": "inv_shoulder_leather_questbloodelf_b_01",
        "count": 1,
        "pct": 1.0,
        "avg_itemLevel": 285.0
      },
      {
        "itemID": 251171,
        "name": "Enthralled Bonespines",
        "icon": "inv_shoulder_leather_dungeonharronir_c_01",
        "count": 1,
        "pct": 1.0,
        "avg_itemLevel": 285.0
      },
      {
        "itemID": 249333,
        "name": "Blooming Barklight Spaulders",
        "icon": "inv_shoulder_leather_raiddruidmidnight_d_01",
        "count": 1,
        "pct": 1.0,
        "avg_itemLevel": 289.0
      }
    ],
    "shirt": [
      {
        "itemID": 251216,
        "name": "Maledict Vest",
        "icon": "inv_chest_leather_dungeonharronir_c_01",
        "count": 30,
        "pct": 30.0,
        "avg_itemLevel": 284.2
      },
      {
        "itemID": 268274,
        "name": "Blinky's Collar",
        "icon": "inv_jewelry_necklace_22",
        "count": 11,
        "pct": 11.0,
        "avg_itemLevel": 1.0
      },
      {
        "itemID": 250027,
        "name": "Trunk of the Luminous Bloom",
        "icon": "inv_chest_leather_raiddruidmidnight_d_01",
        "count": 8,
        "pct": 8.0,
        "avg_itemLevel": 286.9
      },
      {
        "itemID": 244570,
        "name": "Silvermoon Agent's Coat",
        "icon": "inv_chest_leather_questbloodelf_b_01",
        "count": 6,
        "pct": 6.0,
        "avg_itemLevel": 285.0
      },
      {
        "itemID": 52019,
        "name": "Precious's Ribbon",
        "icon": "inv_misc_ribbon_01",
        "count": 4,
        "pct": 4.0,
        "avg_itemLevel": 1.0
      },
      {
        "itemID": 138385,
        "name": "Lucky Shirt",
        "icon": "inv_shirt_02",
        "count": 4,
        "pct": 4.0,
        "avg_itemLevel": 1.0
      },
      {
        "itemID": 11840,
        "name": "Master Builder's Shirt",
        "icon": "inv_shirt_black_01",
        "count": 3,
        "pct": 3.0,
        "avg_itemLevel": 1.0
      },
      {
        "itemID": 151313,
        "name": "Vest of the Void's Embrace",
        "icon": "inv_chest_leather_legiondungeon_c_03",
        "count": 3,
        "pct": 3.0,
        "avg_itemLevel": 284.7
      },
      {
        "itemID": 258586,
        "name": "Bloodfeather Chestguard",
        "icon": "inv_leather_draenordungeon_c_01chest",
        "count": 3,
        "pct": 3.0,
        "avg_itemLevel": 276.0
      },
      {
        "itemID": 6795,
        "name": "White Swashbuckler's Shirt",
        "icon": "inv_shirt_white_01",
        "count": 3,
        "pct": 3.0,
        "avg_itemLevel": 1.0
      }
    ],
    "chest": [
      {
        "itemID": 251216,
        "name": "Maledict Vest",
        "icon": "inv_chest_leather_dungeonharronir_c_01",
        "count": 20,
        "pct": 20.0,
        "avg_itemLevel": 284.9
      },
      {
        "itemID": 249314,
        "name": "Twisted Twilight Sash",
        "icon": "inv_belt_leather_raiddemonhuntermidnight_d_01",
        "count": 14,
        "pct": 14.0,
        "avg_itemLevel": 284.3
      },
      {
        "itemID": 258586,
        "name": "Bloodfeather Chestguard",
        "icon": "inv_leather_draenordungeon_c_01chest",
        "count": 12,
        "pct": 12.0,
        "avg_itemLevel": 282.5
      },
      {
        "itemID": 244573,
        "name": "Silvermoon Agent's Utility Belt",
        "icon": "inv_belt_leather_questbloodelf_b_01",
        "count": 12,
        "pct": 12.0,
        "avg_itemLevel": 285.0
      },
      {
        "itemID": 251166,
        "name": "Falconer's Cinch",
        "icon": "inv_belt_leather_dungeonharronir_c_01",
        "count": 9,
        "pct": 9.0,
        "avg_itemLevel": 281.8
      },
      {
        "itemID": 249374,
        "name": "Scorn-Scarred Shul'ka's Belt",
        "icon": "inv_belt_leather_raidmonkmidnight_d_01",
        "count": 8,
        "pct": 8.0,
        "avg_itemLevel": 284.9
      },
      {
        "itemID": 244570,
        "name": "Silvermoon Agent's Coat",
        "icon": "inv_chest_leather_questbloodelf_b_01",
        "count": 5,
        "pct": 5.0,
        "avg_itemLevel": 285.0
      },
      {
        "itemID": 49806,
        "name": "Flayer's Black Belt",
        "icon": "inv_belt_65",
        "count": 4,
        "pct": 4.0,
        "avg_itemLevel": 276.0
      },
      {
        "itemID": 250027,
        "name": "Trunk of the Luminous Bloom",
        "icon": "inv_chest_leather_raiddruidmidnight_d_01",
        "count": 4,
        "pct": 4.0,
        "avg_itemLevel": 289.0
      },
      {
        "itemID": 249643,
        "name": "Osseoclad Waistbone",
        "icon": "inv_belt_leather_dungeonharronir_c_01",
        "count": 2,
        "pct": 2.0,
        "avg_itemLevel": 276.0
      }
    ],
    "waist": [
      {
        "itemID": 250023,
        "name": "Phloemwraps of the Luminous Bloom",
        "icon": "inv_pant_leather_raiddruidmidnight_d_01",
        "count": 49,
        "pct": 49.0,
        "avg_itemLevel": 286.7
      },
      {
        "itemID": 249314,
        "name": "Twisted Twilight Sash",
        "icon": "inv_belt_leather_raiddemonhuntermidnight_d_01",
        "count": 14,
        "pct": 14.0,
        "avg_itemLevel": 285.6
      },
      {
        "itemID": 244573,
        "name": "Silvermoon Agent's Utility Belt",
        "icon": "inv_belt_leather_questbloodelf_b_01",
        "count": 14,
        "pct": 14.0,
        "avg_itemLevel": 285.0
      },
      {
        "itemID": 251166,
        "name": "Falconer's Cinch",
        "icon": "inv_belt_leather_dungeonharronir_c_01",
        "count": 8,
        "pct": 8.0,
        "avg_itemLevel": 277.6
      },
      {
        "itemID": 249374,
        "name": "Scorn-Scarred Shul'ka's Belt",
        "icon": "inv_belt_leather_raidmonkmidnight_d_01",
        "count": 6,
        "pct": 6.0,
        "avg_itemLevel": 289.0
      },
      {
        "itemID": 260373,
        "name": "Power Stance Breeches",
        "icon": "inv_pant_leather_raidmonkmidnight_d_01",
        "count": 1,
        "pct": 1.0,
        "avg_itemLevel": 289.0
      }
    ],
    "legs": [
      {
        "itemID": 250023,
        "name": "Phloemwraps of the Luminous Bloom",
        "icon": "inv_pant_leather_raiddruidmidnight_d_01",
        "count": 41,
        "pct": 41.0,
        "avg_itemLevel": 287.4
      },
      {
        "itemID": 260372,
        "name": "Nullstrider's Boots",
        "icon": "inv_boot_leather_raidroguemidnight_d_01",
        "count": 17,
        "pct": 17.0,
        "avg_itemLevel": 287.9
      },
      {
        "itemID": 249334,
        "name": "Void-Claimed Shinkickers",
        "icon": "inv_boot_leather_raiddemonhuntermidnight_d_01",
        "count": 15,
        "pct": 15.0,
        "avg_itemLevel": 287.0
      },
      {
        "itemID": 251210,
        "name": "Eclipse Espadrilles",
        "icon": "inv_boot_leather_dungeonharronir_c_01",
        "count": 8,
        "pct": 8.0,
        "avg_itemLevel": 282.5
      },
      {
        "itemID": 250026,
        "name": "Rootslippers of the Luminous Bloom",
        "icon": "inv_boot_leather_raiddruidmidnight_d_01",
        "count": 7,
        "pct": 7.0,
        "avg_itemLevel": 286.1
      },
      {
        "itemID": 251121,
        "name": "Domanaar's Dire Treads",
        "icon": "inv_boot_leather_dungeonharronir_c_01",
        "count": 2,
        "pct": 2.0,
        "avg_itemLevel": 282.5
      },
      {
        "itemID": 260373,
        "name": "Power Stance Breeches",
        "icon": "inv_pant_leather_raidmonkmidnight_d_01",
        "count": 1,
        "pct": 1.0,
        "avg_itemLevel": 289.0
      },
      {
        "itemID": 151317,
        "name": "Footpads of Seeping Dread",
        "icon": "inv_boot_leather_legiondungeon_c_03",
        "count": 1,
        "pct": 1.0,
        "avg_itemLevel": 276.0
      }
    ],
    "feet": [
      {
        "itemID": 244576,
        "name": "Silvermoon Agent's Deflectors",
        "icon": "inv_bracer_leather_questbloodelf_b_01",
        "count": 32,
        "pct": 32.0,
        "avg_itemLevel": 284.6
      },
      {
        "itemID": 260372,
        "name": "Nullstrider's Boots",
        "icon": "inv_boot_leather_raidroguemidnight_d_01",
        "count": 17,
        "pct": 17.0,
        "avg_itemLevel": 286.6
      },
      {
        "itemID": 193714,
        "name": "Frenzyroot Cuffs",
        "icon": "inv_leather_dragondungeon_c_01_bracer",
        "count": 10,
        "pct": 10.0,
        "avg_itemLevel": 278.6
      },
      {
        "itemID": 251210,
        "name": "Eclipse Espadrilles",
        "icon": "inv_boot_leather_dungeonharronir_c_01",
        "count": 7,
        "pct": 7.0,
        "avg_itemLevel": 281.6
      },
      {
        "itemID": 249334,
        "name": "Void-Claimed Shinkickers",
        "icon": "inv_boot_leather_raiddemonhuntermidnight_d_01",
        "count": 6,
        "pct": 6.0,
        "avg_itemLevel": 282.8
      },
      {
        "itemID": 251103,
        "name": "Custodial Cuffs",
        "icon": "inv_bracer_leather_dungeonharronir_c_01",
        "count": 4,
        "pct": 4.0,
        "avg_itemLevel": 276.0
      },
      {
        "itemID": 250020,
        "name": "Bindings of the Luminous Bloom",
        "icon": "inv_bracer_leather_raiddruidmidnight_d_01",
        "count": 4,
        "pct": 4.0,
        "avg_itemLevel": 281.5
      },
      {
        "itemID": 251121,
        "name": "Domanaar's Dire Treads",
        "icon": "inv_boot_leather_dungeonharronir_c_01",
        "count": 4,
        "pct": 4.0,
        "avg_itemLevel": 279.2
      },
      {
        "itemID": 250026,
        "name": "Rootslippers of the Luminous Bloom",
        "icon": "inv_boot_leather_raiddruidmidnight_d_01",
        "count": 3,
        "pct": 3.0,
        "avg_itemLevel": 284.7
      },
      {
        "itemID": 151317,
        "name": "Footpads of Seeping Dread",
        "icon": "inv_boot_leather_legiondungeon_c_03",
        "count": 3,
        "pct": 3.0,
        "avg_itemLevel": 280.3
      }
    ],
    "wrist": [
      {
        "itemID": 250025,
        "name": "Arbortenders of the Luminous Bloom",
        "icon": "inv_glove_leather_raiddruidmidnight_d_01",
        "count": 49,
        "pct": 49.0,
        "avg_itemLevel": 284.4
      },
      {
        "itemID": 244576,
        "name": "Silvermoon Agent's Deflectors",
        "icon": "inv_bracer_leather_questbloodelf_b_01",
        "count": 29,
        "pct": 29.0,
        "avg_itemLevel": 283.7
      },
      {
        "itemID": 250020,
        "name": "Bindings of the Luminous Bloom",
        "icon": "inv_bracer_leather_raiddruidmidnight_d_01",
        "count": 6,
        "pct": 6.0,
        "avg_itemLevel": 278.2
      },
      {
        "itemID": 193714,
        "name": "Frenzyroot Cuffs",
        "icon": "inv_leather_dragondungeon_c_01_bracer",
        "count": 4,
        "pct": 4.0,
        "avg_itemLevel": 276.0
      },
      {
        "itemID": 251103,
        "name": "Custodial Cuffs",
        "icon": "inv_bracer_leather_dungeonharronir_c_01",
        "count": 2,
        "pct": 2.0,
        "avg_itemLevel": 282.5
      },
      {
        "itemID": 251204,
        "name": "Corewright's Zappers",
        "icon": "inv_glove_leather_dungeonharronir_c_01",
        "count": 1,
        "pct": 1.0,
        "avg_itemLevel": 289.0
      },
      {
        "itemID": 249644,
        "name": "Osseoclad Ivory Wrist",
        "icon": "inv_bracer_leather_dungeonharronir_c_01",
        "count": 1,
        "pct": 1.0,
        "avg_itemLevel": 276.0
      }
    ],
    "hands": [
      {
        "itemID": 250025,
        "name": "Arbortenders of the Luminous Bloom",
        "icon": "inv_glove_leather_raiddruidmidnight_d_01",
        "count": 42,
        "pct": 42.0,
        "avg_itemLevel": 284.6
      },
      {
        "itemID": 251093,
        "name": "Omission of Light",
        "icon": "inv_12_trinket_devouring_host_currency1_silver",
        "count": 22,
        "pct": 22.0,
        "avg_itemLevel": 278.7
      },
      {
        "itemID": 251115,
        "name": "Bifurcation Band",
        "icon": "inv_12_trinket_devouring_host_currency2_void",
        "count": 18,
        "pct": 18.0,
        "avg_itemLevel": 276.7
      },
      {
        "itemID": 151311,
        "name": "Band of the Triumvirate",
        "icon": "inv_70_dungeon_ring2b",
        "count": 4,
        "pct": 4.0,
        "avg_itemLevel": 276.0
      },
      {
        "itemID": 249920,
        "name": "Eye of Midnight",
        "icon": "inv_12_jewelry_devouringhost_ring_bronze",
        "count": 3,
        "pct": 3.0,
        "avg_itemLevel": 276.0
      },
      {
        "itemID": 249369,
        "name": "Bond of Light",
        "icon": "inv_12_jewelry_silvermoonelf_ring_blue1",
        "count": 3,
        "pct": 3.0,
        "avg_itemLevel": 284.7
      }
    ],
    "finger1": [
      {
        "itemID": 251093,
        "name": "Omission of Light",
        "icon": "inv_12_trinket_devouring_host_currency1_silver",
        "count": 37,
        "pct": 37.0,
        "avg_itemLevel": 278.8
      },
      {
        "itemID": 251115,
        "name": "Bifurcation Band",
        "icon": "inv_12_trinket_devouring_host_currency2_void",
        "count": 26,
        "pct": 26.0,
        "avg_itemLevel": 276.7
      },
      {
        "itemID": 249369,
        "name": "Bond of Light",
        "icon": "inv_12_jewelry_silvermoonelf_ring_blue1",
        "count": 12,
        "pct": 12.0,
        "avg_itemLevel": 282.9
      },
      {
        "itemID": 240949,
        "name": "Masterwork Sin'dorei Band",
        "icon": "inv_12_profession_jewelcrafting_ring4_gold",
        "count": 7,
        "pct": 7.0,
        "avg_itemLevel": 285.0
      },
      {
        "itemID": 151311,
        "name": "Band of the Triumvirate",
        "icon": "inv_70_dungeon_ring2b",
        "count": 5,
        "pct": 5.0,
        "avg_itemLevel": 279.0
      },
      {
        "itemID": 249920,
        "name": "Eye of Midnight",
        "icon": "inv_12_jewelry_devouringhost_ring_bronze",
        "count": 4,
        "pct": 4.0,
        "avg_itemLevel": 279.2
      },
      {
        "itemID": 251217,
        "name": "Occlusion of Void",
        "icon": "inv_12_trinket_devouring_host_currency1_bronze",
        "count": 1,
        "pct": 1.0,
        "avg_itemLevel": 289.0
      }
    ],
    "finger2": [
      {
        "itemID": 249343,
        "name": "Gaze of the Alnseer",
        "icon": "inv_12_trinket_raid_dreamrift_gazeofthealnseer",
        "count": 23,
        "pct": 23.0,
        "avg_itemLevel": 287.0
      },
      {
        "itemID": 251093,
        "name": "Omission of Light",
        "icon": "inv_12_trinket_devouring_host_currency1_silver",
        "count": 21,
        "pct": 21.0,
        "avg_itemLevel": 278.3
      },
      {
        "itemID": 251115,
        "name": "Bifurcation Band",
        "icon": "inv_12_trinket_devouring_host_currency2_void",
        "count": 13,
        "pct": 13.0,
        "avg_itemLevel": 277.0
      },
      {
        "itemID": 249809,
        "name": "Locus-Walker's Ribbon",
        "icon": "inv_12_trinket_raid_voidspire_int2_locuswalkerslastribbon",
        "count": 12,
        "pct": 12.0,
        "avg_itemLevel": 284.8
      },
      {
        "itemID": 249369,
        "name": "Bond of Light",
        "icon": "inv_12_jewelry_silvermoonelf_ring_blue1",
        "count": 7,
        "pct": 7.0,
        "avg_itemLevel": 284.7
      },
      {
        "itemID": 249341,
        "name": "Volatile Void Suffuser",
        "icon": "inv_12_trinket_raid_voidspire_healer1_volatilevoidsuffuser",
        "count": 6,
        "pct": 6.0,
        "avg_itemLevel": 286.8
      },
      {
        "itemID": 250256,
        "name": "Heart of Wind",
        "icon": "inv_10_jewelcrafting3_soulcage_air",
        "count": 6,
        "pct": 6.0,
        "avg_itemLevel": 282.5
      },
      {
        "itemID": 249346,
        "name": "Vaelgor's Final Stare",
        "icon": "inv_12_trinket_raid_voidspire_int1_voiddragoneye",
        "count": 2,
        "pct": 2.0,
        "avg_itemLevel": 282.5
      },
      {
        "itemID": 249920,
        "name": "Eye of Midnight",
        "icon": "inv_12_jewelry_devouringhost_ring_bronze",
        "count": 1,
        "pct": 1.0,
        "avg_itemLevel": 276.0
      },
      {
        "itemID": 250144,
        "name": "Emberwing Feather",
        "icon": "inv_icon_feather06a",
        "count": 1,
        "pct": 1.0,
        "avg_itemLevel": 276.0
      }
    ],
    "trinket1": [
      {
        "itemID": 249343,
        "name": "Gaze of the Alnseer",
        "icon": "inv_12_trinket_raid_dreamrift_gazeofthealnseer",
        "count": 41,
        "pct": 41.0,
        "avg_itemLevel": 286.6
      },
      {
        "itemID": 250256,
        "name": "Heart of Wind",
        "icon": "inv_10_jewelcrafting3_soulcage_air",
        "count": 17,
        "pct": 17.0,
        "avg_itemLevel": 278.1
      },
      {
        "itemID": 249809,
        "name": "Locus-Walker's Ribbon",
        "icon": "inv_12_trinket_raid_voidspire_int2_locuswalkerslastribbon",
        "count": 15,
        "pct": 15.0,
        "avg_itemLevel": 283.1
      },
      {
        "itemID": 249341,
        "name": "Volatile Void Suffuser",
        "icon": "inv_12_trinket_raid_voidspire_healer1_volatilevoidsuffuser",
        "count": 7,
        "pct": 7.0,
        "avg_itemLevel": 287.9
      },
      {
        "itemID": 249346,
        "name": "Vaelgor's Final Stare",
        "icon": "inv_12_trinket_raid_voidspire_int1_voiddragoneye",
        "count": 5,
        "pct": 5.0,
        "avg_itemLevel": 286.4
      },
      {
        "itemID": 193718,
        "name": "Emerald Coach's Whistle",
        "icon": "inv_misc_head_dragon_green",
        "count": 4,
        "pct": 4.0,
        "avg_itemLevel": 279.2
      },
      {
        "itemID": 249808,
        "name": "Litany of Lightblind Wrath",
        "icon": "inv_12_trinket_raid_voidspire_healer2_litanyoflightblindwrath",
        "count": 2,
        "pct": 2.0,
        "avg_itemLevel": 282.5
      },
      {
        "itemID": 250144,
        "name": "Emberwing Feather",
        "icon": "inv_icon_feather06a",
        "count": 1,
        "pct": 1.0,
        "avg_itemLevel": 276.0
      }
    ],
    "trinket2": [
      {
        "itemID": 239656,
        "name": "Adherent's Silken Shroud",
        "icon": "inv_cape_cloth_questbloodelf_b_01",
        "count": 39,
        "pct": 39.0,
        "avg_itemLevel": 284.7
      },
      {
        "itemID": 249343,
        "name": "Gaze of the Alnseer",
        "icon": "inv_12_trinket_raid_dreamrift_gazeofthealnseer",
        "count": 17,
        "pct": 17.0,
        "avg_itemLevel": 289.1
      },
      {
        "itemID": 249809,
        "name": "Locus-Walker's Ribbon",
        "icon": "inv_12_trinket_raid_voidspire_int2_locuswalkerslastribbon",
        "count": 8,
        "pct": 8.0,
        "avg_itemLevel": 284.1
      },
      {
        "itemID": 250256,
        "name": "Heart of Wind",
        "icon": "inv_10_jewelcrafting3_soulcage_air",
        "count": 8,
        "pct": 8.0,
        "avg_itemLevel": 280.4
      },
      {
        "itemID": 249341,
        "name": "Volatile Void Suffuser",
        "icon": "inv_12_trinket_raid_voidspire_healer1_volatilevoidsuffuser",
        "count": 5,
        "pct": 5.0,
        "avg_itemLevel": 286.2
      },
      {
        "itemID": 249370,
        "name": "Draconic Nullcape",
        "icon": "inv_plate_revendrethraid_d_01_cape",
        "count": 4,
        "pct": 4.0,
        "avg_itemLevel": 281.5
      },
      {
        "itemID": 251206,
        "name": "Fluxweave Cloak",
        "icon": "inv_cape_cloth_dungeonharronir_c_01",
        "count": 3,
        "pct": 3.0,
        "avg_itemLevel": 277.0
      },
      {
        "itemID": 249346,
        "name": "Vaelgor's Final Stare",
        "icon": "inv_12_trinket_raid_voidspire_int1_voiddragoneye",
        "count": 3,
        "pct": 3.0,
        "avg_itemLevel": 289.0
      },
      {
        "itemID": 193712,
        "name": "Potion-Stained Cloak",
        "icon": "inv_leather_dragondungeon_c_01_cape",
        "count": 2,
        "pct": 2.0,
        "avg_itemLevel": 279.0
      },
      {
        "itemID": 250019,
        "name": "Leafdrape of the Luminous Bloom",
        "icon": "inv_cape_leather_raiddruidmidnight_d_01",
        "count": 1,
        "pct": 1.0,
        "avg_itemLevel": 276.0
      }
    ],
    "back": [
      {
        "itemID": 239656,
        "name": "Adherent's Silken Shroud",
        "icon": "inv_cape_cloth_questbloodelf_b_01",
        "count": 25,
        "pct": 25.0,
        "avg_itemLevel": 284.5
      },
      {
        "itemID": 245770,
        "name": "Aln'hara Cane",
        "icon": "inv_staff_2h_dungeonharronir_c_02",
        "count": 21,
        "pct": 21.0,
        "avg_itemLevel": 286.0
      },
      {
        "itemID": 251201,
        "name": "Corespark Multitool",
        "icon": "inv_staff_2h_domanaar_b_01",
        "count": 12,
        "pct": 12.0,
        "avg_itemLevel": 288.7
      },
      {
        "itemID": 249370,
        "name": "Draconic Nullcape",
        "icon": "inv_plate_revendrethraid_d_01_cape",
        "count": 8,
        "pct": 8.0,
        "avg_itemLevel": 289.0
      },
      {
        "itemID": 258047,
        "name": "Spire of the Furious Construct",
        "icon": "invstaff_2h_draenordungeon_c_04",
        "count": 7,
        "pct": 7.0,
        "avg_itemLevel": 290.3
      },
      {
        "itemID": 251206,
        "name": "Fluxweave Cloak",
        "icon": "inv_cape_cloth_dungeonharronir_c_01",
        "count": 3,
        "pct": 3.0,
        "avg_itemLevel": 284.7
      },
      {
        "itemID": 193712,
        "name": "Potion-Stained Cloak",
        "icon": "inv_leather_dragondungeon_c_01_cape",
        "count": 3,
        "pct": 3.0,
        "avg_itemLevel": 280.3
      },
      {
        "itemID": 249293,
        "name": "Weight of Command",
        "icon": "inv_mace_1h_raidmidnight_d_02",
        "count": 2,
        "pct": 2.0,
        "avg_itemLevel": 289.0
      },
      {
        "itemID": 258514,
        "name": "Umbral Spire of Zuraal",
        "icon": "inv_staff_2h_oribosdungeon_c_01",
        "count": 2,
        "pct": 2.0,
        "avg_itemLevel": 289.0
      },
      {
        "itemID": 258050,
        "name": "Arcanic of the High Sage",
        "icon": "inv_hand_1h_draenordungeon_c_02",
        "count": 2,
        "pct": 2.0,
        "avg_itemLevel": 289.0
      }
    ],
    "main_hand": [
      {
        "itemID": 245770,
        "name": "Aln'hara Cane",
        "icon": "inv_staff_2h_dungeonharronir_c_02",
        "count": 17,
        "pct": 17.0,
        "avg_itemLevel": 286.8
      },
      {
        "itemID": 251201,
        "name": "Corespark Multitool",
        "icon": "inv_staff_2h_domanaar_b_01",
        "count": 14,
        "pct": 14.0,
        "avg_itemLevel": 289.6
      },
      {
        "itemID": 258047,
        "name": "Spire of the Furious Construct",
        "icon": "invstaff_2h_draenordungeon_c_04",
        "count": 5,
        "pct": 5.0,
        "avg_itemLevel": 289.0
      },
      {
        "itemID": 249922,
        "name": "Tome of Alnscorned Regret",
        "icon": "inv_offhand_1h_raidmidnight_d_01",
        "count": 3,
        "pct": 3.0,
        "avg_itemLevel": 287.7
      },
      {
        "itemID": 193707,
        "name": "Final Grade",
        "icon": "inv_staff_2h_drakonid_c_01",
        "count": 3,
        "pct": 3.0,
        "avg_itemLevel": 289.0
      },
      {
        "itemID": 258514,
        "name": "Umbral Spire of Zuraal",
        "icon": "inv_staff_2h_oribosdungeon_c_01",
        "count": 2,
        "pct": 2.0,
        "avg_itemLevel": 289.0
      },
      {
        "itemID": 168100,
        "name": "Alliance Tabard",
        "icon": "inv_misc_tabardpvp_01",
        "count": 2,
        "pct": 2.0,
        "avg_itemLevel": 2.0
      },
      {
        "itemID": 249286,
        "name": "Brazier of the Dissonant Dirge",
        "icon": "inv_staff_2h_raidmidnight_d_02",
        "count": 1,
        "pct": 1.0,
        "avg_itemLevel": 289.0
      },
      {
        "itemID": 193709,
        "name": "Vexamus' Expulsion Rod",
        "icon": "inv_offhand_1h_drakonid_c_01",
        "count": 1,
        "pct": 1.0,
        "avg_itemLevel": 289.0
      },
      {
        "itemID": 258472,
        "name": "Rukhran's Solar Reliquary",
        "icon": "inv_offhand_1h_draenordungeon_c_01",
        "count": 1,
        "pct": 1.0,
        "avg_itemLevel": 276.0
      }
    ],
    "off_hand": [
      {
        "itemID": 69210,
        "name": "Renowned Guild Tabard",
        "icon": "inv_epicguildtabard",
        "count": 5,
        "pct": 5.0,
        "avg_itemLevel": 1.0
      },
      {
        "itemID": 65908,
        "name": "Tabard of the Wildhammer Clan",
        "icon": "inv_misc_tabard_wildhammerclan",
        "count": 2,
        "pct": 2.0,
        "avg_itemLevel": 14.0
      },
      {
        "itemID": 49052,
        "name": "Tabard of Conquest",
        "icon": "inv_shirt_guildtabard_01",
        "count": 2,
        "pct": 2.0,
        "avg_itemLevel": 14.0
      },
      {
        "itemID": 65904,
        "name": "Tabard of Ramkahen",
        "icon": "inv_misc_tabard_tolvir",
        "count": 1,
        "pct": 1.0,
        "avg_itemLevel": 14.0
      },
      {
        "itemID": 233290,
        "name": "Sacred Templar's Tabard",
        "icon": "inv_tabard_nightfall_c_01",
        "count": 1,
        "pct": 1.0,
        "avg_itemLevel": 1.0
      },
      {
        "itemID": 198732,
        "name": "Valdrakken Accord Tabard",
        "icon": "inv_tabard_valdrakkenaccord_c_01",
        "count": 1,
        "pct": 1.0,
        "avg_itemLevel": 1.0
      },
      {
        "itemID": 233288,
        "name": "Radiant Recruit's Tabard",
        "icon": "inv_tabard_nightfall_a_01",
        "count": 1,
        "pct": 1.0,
        "avg_itemLevel": 1.0
      },
      {
        "itemID": 210424,
        "name": "Darnassian Tabard",
        "icon": "inv_tabard_darnassus_a_01",
        "count": 1,
        "pct": 1.0,
        "avg_itemLevel": 1.0
      },
      {
        "itemID": 38310,
        "name": "Tabard of the Arcane",
        "icon": "inv_shirt_guildtabard_01",
        "count": 1,
        "pct": 1.0,
        "avg_itemLevel": 1.0
      },
      {
        "itemID": 89196,
        "name": "Theramore Tabard",
        "icon": "inv_shirt_guildtabard_01",
        "count": 1,
        "pct": 1.0,
        "avg_itemLevel": 1.0
      }
    ]
  },
  "race": {},
  "factions": {
    "alliance": 99,
    "horde": 1
  },
  "guilds": [
    {
      "name": "Hyeta",
      "count": 2
    },
    {
      "name": "123",
      "count": 2
    },
    {
      "name": "Muisted",
      "count": 1
    },
    {
      "name": "get help",
      "count": 1
    },
    {
      "name": "Project One",
      "count": 1
    },
    {
      "name": "Beam",
      "count": 1
    },
    {
      "name": "Reversio",
      "count": 1
    },
    {
      "name": "Grizzly Hills Track Team",
      "count": 1
    },
    {
      "name": "Fragglene",
      "count": 1
    },
    {
      "name": "YEP",
      "count": 1
    },
    {
      "name": "Гнев Анархии",
      "count": 1
    },
    {
      "name": "Da Bishes",
      "count": 1
    },
    {
      "name": "Ethical",
      "count": 1
    },
    {
      "name": "Honestly",
      "count": 1
    },
    {
      "name": "Echo",
      "count": 1
    }
  ],
  "stats": {},
  "gems": []
}