{
  "season_id": 2,
  "encounter_id": 3181,
  "boss_name": "Crown of the Cosmos",
  "boss_name_cn": "宇宙之冠",
  "class_name": "Paladin",
  "spec_name": "Retribution",
  "sample_count": 87,
  "dps": {
    "avg": 74354.2,
    "median": 77688.8,
    "p25": 69560.7,
    "p75": 84073.0,
    "max": 99193.2,
    "min": 14116.9,
    "sample_count": 86
  },
  "talents": [
    {
      "build": "e5909983787c",
      "count": 8,
      "pct": 9.2,
      "avg_dps": 78628.6
    },
    {
      "build": "a55c87a0d5c5",
      "count": 5,
      "pct": 5.7,
      "avg_dps": 61677.2
    },
    {
      "build": "8132aa756bbd",
      "count": 3,
      "pct": 3.4,
      "avg_dps": 83458.2
    },
    {
      "build": "0ce7ca9e096d",
      "count": 3,
      "pct": 3.4,
      "avg_dps": 77514.0
    },
    {
      "build": "68b3c260fc46",
      "count": 2,
      "pct": 2.3,
      "avg_dps": 92479.1
    },
    {
      "build": "ae2040056917",
      "count": 2,
      "pct": 2.3,
      "avg_dps": 82567.9
    },
    {
      "build": "5e3bb28665bd",
      "count": 2,
      "pct": 2.3,
      "avg_dps": 80806.5
    },
    {
      "build": "48921c2bf606",
      "count": 2,
      "pct": 2.3,
      "avg_dps": 71967.8
    },
    {
      "build": "febb856c341c",
      "count": 2,
      "pct": 2.3,
      "avg_dps": 53488.9
    },
    {
      "build": "3dc2f313529c",
      "count": 1,
      "pct": 1.1,
      "avg_dps": 99193.2
    },
    {
      "build": "dcaad0a6c775",
      "count": 1,
      "pct": 1.1,
      "avg_dps": 94134.8
    },
    {
      "build": "62c8cc7550e9",
      "count": 1,
      "pct": 1.1,
      "avg_dps": 91542.8
    },
    {
      "build": "fdfac1e79222",
      "count": 1,
      "pct": 1.1,
      "avg_dps": 90761.5
    },
    {
      "build": "a3b4dde41e7c",
      "count": 1,
      "pct": 1.1,
      "avg_dps": 88753.1
    },
    {
      "build": "43ac38daaec6",
      "count": 1,
      "pct": 1.1,
      "avg_dps": 87420.8
    },
    {
      "build": "540df729f8f5",
      "count": 1,
      "pct": 1.1,
      "avg_dps": 87015.6
    },
    {
      "build": "05acff84e7d9",
      "count": 1,
      "pct": 1.1,
      "avg_dps": 86962.0
    },
    {
      "build": "92055d9f1b5f",
      "count": 1,
      "pct": 1.1,
      "avg_dps": 85225.5
    },
    {
      "build": "8c4788800f17",
      "count": 1,
      "pct": 1.1,
      "avg_dps": 84757.8
    },
    {
      "build": "dca51310d746",
      "count": 1,
      "pct": 1.1,
      "avg_dps": 84528.2
    }
  ],
  "gear": {
    "head": [
      {
        "itemID": 249961,
        "name": "Luminant Verdict's Unwavering Gaze",
        "icon": "inv_helm_plate_raidpaladinmidnight_d_01",
        "count": 87,
        "pct": 100.0,
        "avg_itemLevel": 288.4
      }
    ],
    "neck": [
      {
        "itemID": 249337,
        "name": "Ribbon of Coiled Malice",
        "icon": "inv_12_jewelry_devouringhost_necklace_bronze",
        "count": 23,
        "pct": 26.4,
        "avg_itemLevel": 289.0
      },
      {
        "itemID": 250247,
        "name": "Amulet of the Abyssal Hymn",
        "icon": "inv_12_jewelry_devouringhost_necklace_bronze2",
        "count": 19,
        "pct": 21.8,
        "avg_itemLevel": 289.0
      },
      {
        "itemID": 50228,
        "name": "Barbed Ymirheim Choker",
        "icon": "inv_jewelry_necklace_22",
        "count": 16,
        "pct": 18.4,
        "avg_itemLevel": 287.4
      },
      {
        "itemID": 240950,
        "name": "Masterwork Sin'dorei Amulet",
        "icon": "inv_12_profession_jewelcrafting_necklace2_gold",
        "count": 15,
        "pct": 17.2,
        "avg_itemLevel": 285.0
      },
      {
        "itemID": 268291,
        "name": "Rotmire's Sporeheart",
        "icon": "inv_12_jewelry_rutaani_necklace_blue",
        "count": 11,
        "pct": 12.6,
        "avg_itemLevel": 298.0
      },
      {
        "itemID": 249368,
        "name": "Eternal Voidsong Chain",
        "icon": "inv_12_jewelry_silvermoonelf_necklace_blue1",
        "count": 2,
        "pct": 2.3,
        "avg_itemLevel": 289.0
      },
      {
        "itemID": 266314,
        "name": "Novice Combatant's Necklace",
        "icon": "inv_112_raidtrinkets_necklace01_etherealnontechnologicalstyle_terra",
        "count": 1,
        "pct": 1.1,
        "avg_itemLevel": 276.0
      }
    ],
    "shoulder": [
      {
        "itemID": 249959,
        "name": "Luminant Verdict's Providence Watch",
        "icon": "inv_shoulder_plate_raidpaladinmidnight_d_01",
        "count": 85,
        "pct": 97.7,
        "avg_itemLevel": 288.6
      },
      {
        "itemID": 249313,
        "name": "Light-Judged Spaulders",
        "icon": "inv_shoulder_plate_raidpaladinmidnight_d_01",
        "count": 1,
        "pct": 1.1,
        "avg_itemLevel": 289.0
      },
      {
        "itemID": 237835,
        "name": "Spellbreaker's Mantle",
        "icon": "inv_plate_questbloodelf_b_01_shoulder",
        "count": 1,
        "pct": 1.1,
        "avg_itemLevel": 285.0
      }
    ],
    "shirt": [
      {
        "itemID": 249964,
        "name": "Luminant Verdict's Divine Warplate",
        "icon": "inv_chest_plate_raidpaladinmidnight_d_01",
        "count": 37,
        "pct": 42.5,
        "avg_itemLevel": 290.7
      },
      {
        "itemID": 268274,
        "name": "Blinky's Collar",
        "icon": "inv_jewelry_necklace_22",
        "count": 14,
        "pct": 16.1,
        "avg_itemLevel": 1.0
      },
      {
        "itemID": 52019,
        "name": "Precious's Ribbon",
        "icon": "inv_misc_ribbon_01",
        "count": 7,
        "pct": 8.0,
        "avg_itemLevel": 1.0
      },
      {
        "itemID": 151116,
        "name": "Fashionable Undershirt",
        "icon": "inv_shirt_06",
        "count": 6,
        "pct": 6.9,
        "avg_itemLevel": 1.0
      },
      {
        "itemID": 89195,
        "name": "Artisan Officer's Shirt",
        "icon": "inv_shirt03_epic",
        "count": 4,
        "pct": 4.6,
        "avg_itemLevel": 1.0
      },
      {
        "itemID": 138385,
        "name": "Lucky Shirt",
        "icon": "inv_shirt_02",
        "count": 3,
        "pct": 3.4,
        "avg_itemLevel": 1.0
      },
      {
        "itemID": 98543,
        "name": "Wraps of the Blood-Soaked Brawler",
        "icon": "inv_chest_leather_20",
        "count": 3,
        "pct": 3.4,
        "avg_itemLevel": 1.0
      },
      {
        "itemID": 44694,
        "name": "Antiseptic-Soaked Dressing",
        "icon": "inv_misc_bandage_08",
        "count": 2,
        "pct": 2.3,
        "avg_itemLevel": 1.0
      },
      {
        "itemID": 98082,
        "name": "Undisputed Champion's Shirt",
        "icon": "inv_shirt_black_01",
        "count": 1,
        "pct": 1.1,
        "avg_itemLevel": 1.0
      },
      {
        "itemID": 41249,
        "name": "Blue Lumberjack Shirt",
        "icon": "inv_shirt_blue_01",
        "count": 1,
        "pct": 1.1,
        "avg_itemLevel": 1.0
      }
    ],
    "chest": [
      {
        "itemID": 249964,
        "name": "Luminant Verdict's Divine Warplate",
        "icon": "inv_chest_plate_raidpaladinmidnight_d_01",
        "count": 49,
        "pct": 56.3,
        "avg_itemLevel": 290.5
      },
      {
        "itemID": 249380,
        "name": "Hate-Tied Waistchain",
        "icon": "inv_plate_raiddeathknightmidnight_d_01_belt",
        "count": 12,
        "pct": 13.8,
        "avg_itemLevel": 289.0
      },
      {
        "itemID": 249958,
        "name": "Luminant Verdict's Undaunted Emblem",
        "icon": "inv_belt_plate_raidpaladinmidnight_d_01",
        "count": 6,
        "pct": 6.9,
        "avg_itemLevel": 289.0
      },
      {
        "itemID": 249331,
        "name": "Ezzorak's Gloombind",
        "icon": "inv_belt_plate_raidwarriormidnight_d_01",
        "count": 5,
        "pct": 5.7,
        "avg_itemLevel": 289.0
      },
      {
        "itemID": 268289,
        "name": "Girdle of Devouring Rot",
        "icon": "inv_belt_plate_raidpaladinmidnight_d_01",
        "count": 5,
        "pct": 5.7,
        "avg_itemLevel": 298.0
      },
      {
        "itemID": 237830,
        "name": "Spellbreaker's Girdle",
        "icon": "inv_plate_questbloodelf_b_01_belt",
        "count": 5,
        "pct": 5.7,
        "avg_itemLevel": 285.0
      },
      {
        "itemID": 151327,
        "name": "Girdle of the Shadowguard",
        "icon": "inv_belt_plate_legiondungeon_c_03",
        "count": 2,
        "pct": 2.3,
        "avg_itemLevel": 289.0
      },
      {
        "itemID": 249309,
        "name": "Sunbound Breastplate",
        "icon": "inv_chest_plate_raidpaladinmidnight_d_01",
        "count": 1,
        "pct": 1.1,
        "avg_itemLevel": 289.0
      },
      {
        "itemID": 49808,
        "name": "Bent Gold Belt",
        "icon": "inv_belt_70",
        "count": 1,
        "pct": 1.1,
        "avg_itemLevel": 289.0
      },
      {
        "itemID": 251112,
        "name": "Shadowsplit Girdle",
        "icon": "inv_belt_plate_dungeonharronir_c_01",
        "count": 1,
        "pct": 1.1,
        "avg_itemLevel": 289.0
      }
    ],
    "waist": [
      {
        "itemID": 249960,
        "name": "Luminant Verdict's Greaves",
        "icon": "inv_pant_plate_raidpaladinmidnight_d_01",
        "count": 35,
        "pct": 40.2,
        "avg_itemLevel": 288.1
      },
      {
        "itemID": 249958,
        "name": "Luminant Verdict's Undaunted Emblem",
        "icon": "inv_belt_plate_raidpaladinmidnight_d_01",
        "count": 17,
        "pct": 19.5,
        "avg_itemLevel": 289.0
      },
      {
        "itemID": 249380,
        "name": "Hate-Tied Waistchain",
        "icon": "inv_plate_raiddeathknightmidnight_d_01_belt",
        "count": 12,
        "pct": 13.8,
        "avg_itemLevel": 287.9
      },
      {
        "itemID": 237830,
        "name": "Spellbreaker's Girdle",
        "icon": "inv_plate_questbloodelf_b_01_belt",
        "count": 11,
        "pct": 12.6,
        "avg_itemLevel": 285.0
      },
      {
        "itemID": 268289,
        "name": "Girdle of Devouring Rot",
        "icon": "inv_belt_plate_raidpaladinmidnight_d_01",
        "count": 6,
        "pct": 6.9,
        "avg_itemLevel": 298.0
      },
      {
        "itemID": 249331,
        "name": "Ezzorak's Gloombind",
        "icon": "inv_belt_plate_raidwarriormidnight_d_01",
        "count": 4,
        "pct": 4.6,
        "avg_itemLevel": 289.0
      },
      {
        "itemID": 249915,
        "name": "Extinction Guards",
        "icon": "inv_plate_raiddeathknightmidnight_d_01_pant",
        "count": 2,
        "pct": 2.3,
        "avg_itemLevel": 289.0
      }
    ],
    "legs": [
      {
        "itemID": 249960,
        "name": "Luminant Verdict's Greaves",
        "icon": "inv_pant_plate_raidpaladinmidnight_d_01",
        "count": 47,
        "pct": 54.0,
        "avg_itemLevel": 289.0
      },
      {
        "itemID": 249381,
        "name": "Greaves of the Unformed",
        "icon": "inv_boot_plate_raidwarriormidnight_d_01",
        "count": 28,
        "pct": 32.2,
        "avg_itemLevel": 288.5
      },
      {
        "itemID": 249332,
        "name": "Parasite Stompers",
        "icon": "inv_boot_plate_raidpaladinmidnight_d_01",
        "count": 4,
        "pct": 4.6,
        "avg_itemLevel": 289.0
      },
      {
        "itemID": 249963,
        "name": "Luminant Verdict's Sabatons",
        "icon": "inv_boot_plate_raidpaladinmidnight_d_01",
        "count": 3,
        "pct": 3.4,
        "avg_itemLevel": 289.0
      },
      {
        "itemID": 249311,
        "name": "Lightblood Greaves",
        "icon": "inv_pant_plate_raidpaladinmidnight_d_01",
        "count": 2,
        "pct": 2.3,
        "avg_itemLevel": 289.0
      },
      {
        "itemID": 249915,
        "name": "Extinction Guards",
        "icon": "inv_plate_raiddeathknightmidnight_d_01_pant",
        "count": 1,
        "pct": 1.1,
        "avg_itemLevel": 289.0
      },
      {
        "itemID": 237828,
        "name": "Spellbreaker's March",
        "icon": "inv_plate_questbloodelf_b_01_boot",
        "count": 1,
        "pct": 1.1,
        "avg_itemLevel": 285.0
      },
      {
        "itemID": 251169,
        "name": "Footwraps of Ill-Fate",
        "icon": "inv_boot_plate_dungeonharronir_c_01",
        "count": 1,
        "pct": 1.1,
        "avg_itemLevel": 289.0
      }
    ],
    "feet": [
      {
        "itemID": 249381,
        "name": "Greaves of the Unformed",
        "icon": "inv_boot_plate_raidwarriormidnight_d_01",
        "count": 44,
        "pct": 50.6,
        "avg_itemLevel": 289.0
      },
      {
        "itemID": 237834,
        "name": "Spellbreaker's Bracers",
        "icon": "inv_plate_questbloodelf_b_01_bracer",
        "count": 26,
        "pct": 29.9,
        "avg_itemLevel": 284.5
      },
      {
        "itemID": 249326,
        "name": "Light's March Bracers",
        "icon": "inv_bracer_plate_raidwarriormidnight_d_01",
        "count": 5,
        "pct": 5.7,
        "avg_itemLevel": 289.0
      },
      {
        "itemID": 249963,
        "name": "Luminant Verdict's Sabatons",
        "icon": "inv_boot_plate_raidpaladinmidnight_d_01",
        "count": 3,
        "pct": 3.4,
        "avg_itemLevel": 289.0
      },
      {
        "itemID": 249957,
        "name": "Luminant Verdict's Cuffs",
        "icon": "inv_bracer_plate_raidpaladinmidnight_d_01",
        "count": 3,
        "pct": 3.4,
        "avg_itemLevel": 289.0
      },
      {
        "itemID": 263193,
        "name": "Trollhunter's Bands",
        "icon": "inv_bracer_plate_dungeonharronir_c_01",
        "count": 3,
        "pct": 3.4,
        "avg_itemLevel": 289.0
      },
      {
        "itemID": 251169,
        "name": "Footwraps of Ill-Fate",
        "icon": "inv_boot_plate_dungeonharronir_c_01",
        "count": 1,
        "pct": 1.1,
        "avg_itemLevel": 289.0
      },
      {
        "itemID": 251107,
        "name": "Oathsworn Stompers",
        "icon": "inv_boot_plate_dungeonharronir_c_01",
        "count": 1,
        "pct": 1.1,
        "avg_itemLevel": 289.0
      },
      {
        "itemID": 249332,
        "name": "Parasite Stompers",
        "icon": "inv_boot_plate_raidpaladinmidnight_d_01",
        "count": 1,
        "pct": 1.1,
        "avg_itemLevel": 289.0
      }
    ],
    "wrist": [
      {
        "itemID": 237834,
        "name": "Spellbreaker's Bracers",
        "icon": "inv_plate_questbloodelf_b_01_bracer",
        "count": 37,
        "pct": 42.5,
        "avg_itemLevel": 285.0
      },
      {
        "itemID": 151332,
        "name": "Voidclaw Gauntlets",
        "icon": "inv_glove_plate_legiondungeon_c_03",
        "count": 16,
        "pct": 18.4,
        "avg_itemLevel": 289.0
      },
      {
        "itemID": 258583,
        "name": "Incarnadine Gauntlets",
        "icon": "inv_glove_plate_draenordungeon_c_01",
        "count": 6,
        "pct": 6.9,
        "avg_itemLevel": 286.8
      },
      {
        "itemID": 249957,
        "name": "Luminant Verdict's Cuffs",
        "icon": "inv_bracer_plate_raidpaladinmidnight_d_01",
        "count": 5,
        "pct": 5.7,
        "avg_itemLevel": 286.4
      },
      {
        "itemID": 249962,
        "name": "Luminant Verdict's Gauntlets",
        "icon": "inv_glove_plate_raidpaladinmidnight_d_01",
        "count": 5,
        "pct": 5.7,
        "avg_itemLevel": 289.0
      },
      {
        "itemID": 263193,
        "name": "Trollhunter's Bands",
        "icon": "inv_bracer_plate_dungeonharronir_c_01",
        "count": 4,
        "pct": 4.6,
        "avg_itemLevel": 289.0
      },
      {
        "itemID": 249326,
        "name": "Light's March Bracers",
        "icon": "inv_bracer_plate_raidwarriormidnight_d_01",
        "count": 4,
        "pct": 4.6,
        "avg_itemLevel": 285.8
      },
      {
        "itemID": 249307,
        "name": "Emberborn Grasps",
        "icon": "inv_glove_plate_raidpaladinmidnight_d_01",
        "count": 4,
        "pct": 4.6,
        "avg_itemLevel": 287.2
      },
      {
        "itemID": 237836,
        "name": "Spellbreaker's Resolve",
        "icon": "inv_plate_questbloodelf_b_01_glove",
        "count": 3,
        "pct": 3.4,
        "avg_itemLevel": 280.7
      },
      {
        "itemID": 251081,
        "name": "Embergrove Grasps",
        "icon": "inv_glove_plate_dungeonharronir_c_01",
        "count": 3,
        "pct": 3.4,
        "avg_itemLevel": 289.0
      }
    ],
    "hands": [
      {
        "itemID": 151332,
        "name": "Voidclaw Gauntlets",
        "icon": "inv_glove_plate_legiondungeon_c_03",
        "count": 28,
        "pct": 32.2,
        "avg_itemLevel": 288.5
      },
      {
        "itemID": 193708,
        "name": "Platinum Star Band",
        "icon": "inv_10_dungeonjewelry_explorer_ring_1_color1",
        "count": 13,
        "pct": 14.9,
        "avg_itemLevel": 287.0
      },
      {
        "itemID": 249962,
        "name": "Luminant Verdict's Gauntlets",
        "icon": "inv_glove_plate_raidpaladinmidnight_d_01",
        "count": 11,
        "pct": 12.6,
        "avg_itemLevel": 289.0
      },
      {
        "itemID": 251217,
        "name": "Occlusion of Void",
        "icon": "inv_12_trinket_devouring_host_currency1_bronze",
        "count": 6,
        "pct": 6.9,
        "avg_itemLevel": 289.0
      },
      {
        "itemID": 258583,
        "name": "Incarnadine Gauntlets",
        "icon": "inv_glove_plate_draenordungeon_c_01",
        "count": 6,
        "pct": 6.9,
        "avg_itemLevel": 289.0
      },
      {
        "itemID": 251093,
        "name": "Omission of Light",
        "icon": "inv_12_trinket_devouring_host_currency1_silver",
        "count": 4,
        "pct": 4.6,
        "avg_itemLevel": 289.0
      },
      {
        "itemID": 249369,
        "name": "Bond of Light",
        "icon": "inv_12_jewelry_silvermoonelf_ring_blue1",
        "count": 4,
        "pct": 4.6,
        "avg_itemLevel": 289.0
      },
      {
        "itemID": 249307,
        "name": "Emberborn Grasps",
        "icon": "inv_glove_plate_raidpaladinmidnight_d_01",
        "count": 3,
        "pct": 3.4,
        "avg_itemLevel": 289.0
      },
      {
        "itemID": 251081,
        "name": "Embergrove Grasps",
        "icon": "inv_glove_plate_dungeonharronir_c_01",
        "count": 2,
        "pct": 2.3,
        "avg_itemLevel": 289.0
      },
      {
        "itemID": 240949,
        "name": "Masterwork Sin'dorei Band",
        "icon": "inv_12_profession_jewelcrafting_ring4_gold",
        "count": 2,
        "pct": 2.3,
        "avg_itemLevel": 285.0
      }
    ],
    "finger1": [
      {
        "itemID": 251217,
        "name": "Occlusion of Void",
        "icon": "inv_12_trinket_devouring_host_currency1_bronze",
        "count": 20,
        "pct": 23.0,
        "avg_itemLevel": 288.4
      },
      {
        "itemID": 193708,
        "name": "Platinum Star Band",
        "icon": "inv_10_dungeonjewelry_explorer_ring_1_color1",
        "count": 13,
        "pct": 14.9,
        "avg_itemLevel": 289.0
      },
      {
        "itemID": 251093,
        "name": "Omission of Light",
        "icon": "inv_12_trinket_devouring_host_currency1_silver",
        "count": 12,
        "pct": 13.8,
        "avg_itemLevel": 289.0
      },
      {
        "itemID": 249919,
        "name": "Sin'dorei Band of Hope",
        "icon": "inv_12_jewelry_silvermoonelf_ring_red1",
        "count": 11,
        "pct": 12.6,
        "avg_itemLevel": 287.8
      },
      {
        "itemID": 249336,
        "name": "Signet of the Starved Beast",
        "icon": "inv_12_jewelry_devouringhost_ring_silver2",
        "count": 6,
        "pct": 6.9,
        "avg_itemLevel": 289.0
      },
      {
        "itemID": 268290,
        "name": "Sporecaller's Blooming Loop",
        "icon": "inv_12_jewelry_rutaani_ring_blue",
        "count": 6,
        "pct": 6.9,
        "avg_itemLevel": 298.0
      },
      {
        "itemID": 251513,
        "name": "Loa Worshiper's Band",
        "icon": "inv_12_profession_jewelcrafting_ring3_silver",
        "count": 6,
        "pct": 6.9,
        "avg_itemLevel": 285.0
      },
      {
        "itemID": 240949,
        "name": "Masterwork Sin'dorei Band",
        "icon": "inv_12_profession_jewelcrafting_ring4_gold",
        "count": 6,
        "pct": 6.9,
        "avg_itemLevel": 285.0
      },
      {
        "itemID": 249369,
        "name": "Bond of Light",
        "icon": "inv_12_jewelry_silvermoonelf_ring_blue1",
        "count": 3,
        "pct": 3.4,
        "avg_itemLevel": 289.0
      },
      {
        "itemID": 251115,
        "name": "Bifurcation Band",
        "icon": "inv_12_trinket_devouring_host_currency2_void",
        "count": 2,
        "pct": 2.3,
        "avg_itemLevel": 282.5
      }
    ],
    "finger2": [
      {
        "itemID": 193701,
        "name": "Algeth'ar Puzzle Box",
        "icon": "inv_misc_enggizmos_18",
        "count": 23,
        "pct": 26.4,
        "avg_itemLevel": 297.6
      },
      {
        "itemID": 251093,
        "name": "Omission of Light",
        "icon": "inv_12_trinket_devouring_host_currency1_silver",
        "count": 14,
        "pct": 16.1,
        "avg_itemLevel": 288.1
      },
      {
        "itemID": 249343,
        "name": "Gaze of the Alnseer",
        "icon": "inv_12_trinket_raid_dreamrift_gazeofthealnseer",
        "count": 11,
        "pct": 12.6,
        "avg_itemLevel": 298.0
      },
      {
        "itemID": 251217,
        "name": "Occlusion of Void",
        "icon": "inv_12_trinket_devouring_host_currency1_bronze",
        "count": 9,
        "pct": 10.3,
        "avg_itemLevel": 289.0
      },
      {
        "itemID": 193708,
        "name": "Platinum Star Band",
        "icon": "inv_10_dungeonjewelry_explorer_ring_1_color1",
        "count": 6,
        "pct": 6.9,
        "avg_itemLevel": 289.0
      },
      {
        "itemID": 249919,
        "name": "Sin'dorei Band of Hope",
        "icon": "inv_12_jewelry_silvermoonelf_ring_red1",
        "count": 6,
        "pct": 6.9,
        "avg_itemLevel": 286.8
      },
      {
        "itemID": 251513,
        "name": "Loa Worshiper's Band",
        "icon": "inv_12_profession_jewelcrafting_ring3_silver",
        "count": 5,
        "pct": 5.7,
        "avg_itemLevel": 285.0
      },
      {
        "itemID": 249336,
        "name": "Signet of the Starved Beast",
        "icon": "inv_12_jewelry_devouringhost_ring_silver2",
        "count": 5,
        "pct": 5.7,
        "avg_itemLevel": 289.0
      },
      {
        "itemID": 249369,
        "name": "Bond of Light",
        "icon": "inv_12_jewelry_silvermoonelf_ring_blue1",
        "count": 2,
        "pct": 2.3,
        "avg_itemLevel": 289.0
      },
      {
        "itemID": 268290,
        "name": "Sporecaller's Blooming Loop",
        "icon": "inv_12_jewelry_rutaani_ring_blue",
        "count": 2,
        "pct": 2.3,
        "avg_itemLevel": 298.0
      }
    ],
    "trinket1": [
      {
        "itemID": 193701,
        "name": "Algeth'ar Puzzle Box",
        "icon": "inv_misc_enggizmos_18",
        "count": 39,
        "pct": 44.8,
        "avg_itemLevel": 297.1
      },
      {
        "itemID": 249343,
        "name": "Gaze of the Alnseer",
        "icon": "inv_12_trinket_raid_dreamrift_gazeofthealnseer",
        "count": 32,
        "pct": 36.8,
        "avg_itemLevel": 298.0
      },
      {
        "itemID": 260235,
        "name": "Umbral Plume",
        "icon": "inv_12_dualityphoenix_void_feather",
        "count": 10,
        "pct": 11.5,
        "avg_itemLevel": 296.7
      },
      {
        "itemID": 249806,
        "name": "Radiant Plume",
        "icon": "inv_12_dualityphoenix_holy_feather",
        "count": 3,
        "pct": 3.4,
        "avg_itemLevel": 298.0
      },
      {
        "itemID": 249342,
        "name": "Heart of Ancient Hunger",
        "icon": "inv_12_trinket_raid_voidspire_strdps_hearthofancienthunger",
        "count": 2,
        "pct": 2.3,
        "avg_itemLevel": 298.0
      },
      {
        "itemID": 252420,
        "name": "Solarflare Prism",
        "icon": "inv_enchant_shardbrilliantlarge",
        "count": 1,
        "pct": 1.1,
        "avg_itemLevel": 282.0
      }
    ],
    "trinket2": [
      {
        "itemID": 239656,
        "name": "Adherent's Silken Shroud",
        "icon": "inv_cape_cloth_questbloodelf_b_01",
        "count": 24,
        "pct": 27.6,
        "avg_itemLevel": 285.0
      },
      {
        "itemID": 193701,
        "name": "Algeth'ar Puzzle Box",
        "icon": "inv_misc_enggizmos_18",
        "count": 22,
        "pct": 25.3,
        "avg_itemLevel": 297.4
      },
      {
        "itemID": 249343,
        "name": "Gaze of the Alnseer",
        "icon": "inv_12_trinket_raid_dreamrift_gazeofthealnseer",
        "count": 16,
        "pct": 18.4,
        "avg_itemLevel": 298.0
      },
      {
        "itemID": 260235,
        "name": "Umbral Plume",
        "icon": "inv_12_dualityphoenix_void_feather",
        "count": 8,
        "pct": 9.2,
        "avg_itemLevel": 298.0
      },
      {
        "itemID": 249370,
        "name": "Draconic Nullcape",
        "icon": "inv_plate_revendrethraid_d_01_cape",
        "count": 4,
        "pct": 4.6,
        "avg_itemLevel": 287.2
      },
      {
        "itemID": 258575,
        "name": "Rigid Scale Greatcloak",
        "icon": "inv_cape_draenordungeon_c_02_plate",
        "count": 3,
        "pct": 3.4,
        "avg_itemLevel": 289.0
      },
      {
        "itemID": 249335,
        "name": "Imperator's Banner",
        "icon": "inv_plate_raiddeathknightmidnight_d_01_cape",
        "count": 3,
        "pct": 3.4,
        "avg_itemLevel": 289.0
      },
      {
        "itemID": 249806,
        "name": "Radiant Plume",
        "icon": "inv_12_dualityphoenix_holy_feather",
        "count": 2,
        "pct": 2.3,
        "avg_itemLevel": 293.5
      },
      {
        "itemID": 260312,
        "name": "Defiant Defender's Drape",
        "icon": "inv_cape_plate_dungeonharronir_c_01",
        "count": 1,
        "pct": 1.1,
        "avg_itemLevel": 289.0
      },
      {
        "itemID": 193712,
        "name": "Potion-Stained Cloak",
        "icon": "inv_leather_dragondungeon_c_01_cape",
        "count": 1,
        "pct": 1.1,
        "avg_itemLevel": 289.0
      }
    ],
    "back": [
      {
        "itemID": 239656,
        "name": "Adherent's Silken Shroud",
        "icon": "inv_cape_cloth_questbloodelf_b_01",
        "count": 38,
        "pct": 43.7,
        "avg_itemLevel": 285.0
      },
      {
        "itemID": 249277,
        "name": "Bellamy's Final Judgement",
        "icon": "inv_mace_2h_raidmidnight_d_01",
        "count": 19,
        "pct": 21.8,
        "avg_itemLevel": 298.0
      },
      {
        "itemID": 193716,
        "name": "Algeth'ar Hedgecleaver",
        "icon": "inv_axe_2h_drakonoid_c_01",
        "count": 6,
        "pct": 6.9,
        "avg_itemLevel": 298.0
      },
      {
        "itemID": 237846,
        "name": "Blood Knight's Warblade",
        "icon": "inv_sword_2h_questbloodelf_b_01",
        "count": 6,
        "pct": 6.9,
        "avg_itemLevel": 295.0
      },
      {
        "itemID": 258575,
        "name": "Rigid Scale Greatcloak",
        "icon": "inv_cape_draenordungeon_c_02_plate",
        "count": 6,
        "pct": 6.9,
        "avg_itemLevel": 289.0
      },
      {
        "itemID": 249370,
        "name": "Draconic Nullcape",
        "icon": "inv_plate_revendrethraid_d_01_cape",
        "count": 3,
        "pct": 3.4,
        "avg_itemLevel": 289.0
      },
      {
        "itemID": 251168,
        "name": "Liferipper's Cutlass",
        "icon": "inv_sword_2h_dungeonharronir_c_01",
        "count": 3,
        "pct": 3.4,
        "avg_itemLevel": 298.0
      },
      {
        "itemID": 193712,
        "name": "Potion-Stained Cloak",
        "icon": "inv_leather_dragondungeon_c_01_cape",
        "count": 1,
        "pct": 1.1,
        "avg_itemLevel": 289.0
      },
      {
        "itemID": 251206,
        "name": "Fluxweave Cloak",
        "icon": "inv_cape_cloth_dungeonharronir_c_01",
        "count": 1,
        "pct": 1.1,
        "avg_itemLevel": 289.0
      },
      {
        "itemID": 237842,
        "name": "Bloomforged Greataxe",
        "icon": "inv_axe_2h_dungeonharronir_c_01",
        "count": 1,
        "pct": 1.1,
        "avg_itemLevel": 295.0
      }
    ],
    "main_hand": [
      {
        "itemID": 249277,
        "name": "Bellamy's Final Judgement",
        "icon": "inv_mace_2h_raidmidnight_d_01",
        "count": 24,
        "pct": 27.6,
        "avg_itemLevel": 298.0
      },
      {
        "itemID": 251168,
        "name": "Liferipper's Cutlass",
        "icon": "inv_sword_2h_dungeonharronir_c_01",
        "count": 17,
        "pct": 19.5,
        "avg_itemLevel": 298.0
      },
      {
        "itemID": 193716,
        "name": "Algeth'ar Hedgecleaver",
        "icon": "inv_axe_2h_drakonoid_c_01",
        "count": 3,
        "pct": 3.4,
        "avg_itemLevel": 298.0
      },
      {
        "itemID": 49802,
        "name": "Garfrost's Two-Ton Hammer",
        "icon": "inv_mace_83",
        "count": 3,
        "pct": 3.4,
        "avg_itemLevel": 298.0
      },
      {
        "itemID": 46874,
        "name": "Argent Crusader's Tabard",
        "icon": "inv_shirt_guildtabard_01",
        "count": 2,
        "pct": 2.3,
        "avg_itemLevel": 1.0
      },
      {
        "itemID": 237846,
        "name": "Blood Knight's Warblade",
        "icon": "inv_sword_2h_questbloodelf_b_01",
        "count": 2,
        "pct": 2.3,
        "avg_itemLevel": 295.0
      },
      {
        "itemID": 233288,
        "name": "Radiant Recruit's Tabard",
        "icon": "inv_tabard_nightfall_a_01",
        "count": 2,
        "pct": 2.3,
        "avg_itemLevel": 1.0
      },
      {
        "itemID": 167811,
        "name": "Brawler's Guild Tabard",
        "icon": "inv_tabard_brawlersguildalliance",
        "count": 1,
        "pct": 1.1,
        "avg_itemLevel": 1.0
      },
      {
        "itemID": 210501,
        "name": "Dream Wardens Tabard",
        "icon": "inv_tabard_denizens_b_01",
        "count": 1,
        "pct": 1.1,
        "avg_itemLevel": 1.0
      },
      {
        "itemID": 52252,
        "name": "Tabard of the Lightbringer",
        "icon": "inv_shirt_guildtabard_01",
        "count": 1,
        "pct": 1.1,
        "avg_itemLevel": 14.0
      }
    ],
    "off_hand": [
      {
        "itemID": 52252,
        "name": "Tabard of the Lightbringer",
        "icon": "inv_shirt_guildtabard_01",
        "count": 14,
        "pct": 16.1,
        "avg_itemLevel": 14.0
      },
      {
        "itemID": 46874,
        "name": "Argent Crusader's Tabard",
        "icon": "inv_shirt_guildtabard_01",
        "count": 3,
        "pct": 3.4,
        "avg_itemLevel": 1.0
      },
      {
        "itemID": 205286,
        "name": "Loamm Niffen Tabard",
        "icon": "inv_tabard_niffen_b_01_blue",
        "count": 2,
        "pct": 2.3,
        "avg_itemLevel": 1.0
      },
      {
        "itemID": 5976,
        "name": "Guild Tabard",
        "icon": "inv_shirt_guildtabard_01",
        "count": 2,
        "pct": 2.3,
        "avg_itemLevel": 1.0
      },
      {
        "itemID": 69210,
        "name": "Renowned Guild Tabard",
        "icon": "inv_epicguildtabard",
        "count": 1,
        "pct": 1.1,
        "avg_itemLevel": 1.0
      },
      {
        "itemID": 25549,
        "name": "Blood Knight Tabard",
        "icon": "inv_shirt_guildtabard_01",
        "count": 1,
        "pct": 1.1,
        "avg_itemLevel": 14.0
      },
      {
        "itemID": 118365,
        "name": "Stormwind Tabard",
        "icon": "inv_misc_tabardpvp_03",
        "count": 1,
        "pct": 1.1,
        "avg_itemLevel": 15.0
      },
      {
        "itemID": 40643,
        "name": "Tabard of the Achiever",
        "icon": "inv_chest_cloth_30",
        "count": 1,
        "pct": 1.1,
        "avg_itemLevel": 1.0
      },
      {
        "itemID": 140577,
        "name": "Court of Farondis Tabard",
        "icon": "inv_tabard_a_91courtfarondis",
        "count": 1,
        "pct": 1.1,
        "avg_itemLevel": 15.0
      },
      {
        "itemID": 178991,
        "name": "Tabard of the Ascended",
        "icon": "inv_tabard_bastion_d_01",
        "count": 1,
        "pct": 1.1,
        "avg_itemLevel": 1.0
      }
    ]
  },
  "race": {},
  "factions": {
    "horde": 38,
    "alliance": 49
  },
  "guilds": [
    {
      "name": "Enrage Timer",
      "count": 2
    },
    {
      "name": "Commit",
      "count": 2
    },
    {
      "name": "Defenestrate",
      "count": 2
    },
    {
      "name": "One Shared Brain Cell",
      "count": 2
    },
    {
      "name": "Knights Who Say Nih",
      "count": 2
    },
    {
      "name": "Unic",
      "count": 2
    },
    {
      "name": "Twelve Step Program",
      "count": 2
    },
    {
      "name": "Lzuruha",
      "count": 2
    },
    {
      "name": "Ascendancy",
      "count": 2
    },
    {
      "name": "BIG PULL ET AU LIT",
      "count": 1
    },
    {
      "name": "Myth",
      "count": 1
    },
    {
      "name": "Vibrant",
      "count": 1
    },
    {
      "name": "No Skill",
      "count": 1
    },
    {
      "name": "Ashen Dominion",
      "count": 1
    },
    {
      "name": "Most Hated",
      "count": 1
    }
  ],
  "kill_time": {
    "avg": 480362.8,
    "median": 488908.0,
    "p25": 459358.5,
    "p75": 502806.5
  },
  "stats": {},
  "gems": []
}