{
  "season_id": 2,
  "encounter_id": 3159,
  "boss_name": "Rotmire",
  "boss_name_cn": "烂泥沼泽",
  "class_name": "DemonHunter",
  "spec_name": "Vengeance",
  "sample_count": 100,
  "dps": {
    "avg": 89770.9,
    "median": 87633.6,
    "p25": 83421.3,
    "p75": 93944.3,
    "max": 119331.1,
    "min": 81791.8,
    "sample_count": 100
  },
  "talents": [
    {
      "build": "dcab1050833a",
      "count": 4,
      "pct": 4.0,
      "avg_dps": 89285.4
    },
    {
      "build": "dc83e9f02185",
      "count": 3,
      "pct": 3.0,
      "avg_dps": 89220.0
    },
    {
      "build": "70aad1ca04f4",
      "count": 2,
      "pct": 2.0,
      "avg_dps": 96644.8
    },
    {
      "build": "26c2899a5b87",
      "count": 2,
      "pct": 2.0,
      "avg_dps": 89434.2
    },
    {
      "build": "59af4d5b9128",
      "count": 2,
      "pct": 2.0,
      "avg_dps": 82238.1
    },
    {
      "build": "632195bedb0a",
      "count": 1,
      "pct": 1.0,
      "avg_dps": 119331.1
    },
    {
      "build": "70299c34fcfc",
      "count": 1,
      "pct": 1.0,
      "avg_dps": 113213.1
    },
    {
      "build": "64397aa689cd",
      "count": 1,
      "pct": 1.0,
      "avg_dps": 107564.6
    },
    {
      "build": "7ac5a7964f65",
      "count": 1,
      "pct": 1.0,
      "avg_dps": 106074.9
    },
    {
      "build": "7bf44a3a3816",
      "count": 1,
      "pct": 1.0,
      "avg_dps": 104861.3
    },
    {
      "build": "a870bfc4475c",
      "count": 1,
      "pct": 1.0,
      "avg_dps": 103552.0
    },
    {
      "build": "3464c6ed4bc6",
      "count": 1,
      "pct": 1.0,
      "avg_dps": 103331.2
    },
    {
      "build": "b84c3f820802",
      "count": 1,
      "pct": 1.0,
      "avg_dps": 102810.5
    },
    {
      "build": "f8a3164cebbc",
      "count": 1,
      "pct": 1.0,
      "avg_dps": 99319.1
    },
    {
      "build": "8efefa9fc2c3",
      "count": 1,
      "pct": 1.0,
      "avg_dps": 97742.9
    },
    {
      "build": "74d420a8f2b9",
      "count": 1,
      "pct": 1.0,
      "avg_dps": 97261.2
    },
    {
      "build": "52ef2a92286b",
      "count": 1,
      "pct": 1.0,
      "avg_dps": 96974.2
    },
    {
      "build": "60e1a90210ef",
      "count": 1,
      "pct": 1.0,
      "avg_dps": 96286.3
    },
    {
      "build": "eee95d442fdf",
      "count": 1,
      "pct": 1.0,
      "avg_dps": 96100.6
    },
    {
      "build": "1b3c69a97ab7",
      "count": 1,
      "pct": 1.0,
      "avg_dps": 95489.5
    }
  ],
  "gear": {},
  "race": {},
  "factions": {
    "alliance": 62,
    "horde": 38
  },
  "guilds": [
    {
      "name": "Primal Instinct",
      "count": 2
    },
    {
      "name": "Pull is Live",
      "count": 2
    },
    {
      "name": "Pass The Brain Cell",
      "count": 2
    },
    {
      "name": "Hogs of War",
      "count": 1
    },
    {
      "name": "Volatile",
      "count": 1
    },
    {
      "name": "Кайзер",
      "count": 1
    },
    {
      "name": "Open Rebellion",
      "count": 1
    },
    {
      "name": "Frequency",
      "count": 1
    },
    {
      "name": "Moron",
      "count": 1
    },
    {
      "name": "Terra",
      "count": 1
    },
    {
      "name": "Game Over",
      "count": 1
    },
    {
      "name": "PXXR GVNG",
      "count": 1
    },
    {
      "name": "Zênith",
      "count": 1
    },
    {
      "name": "A Friends Guild",
      "count": 1
    },
    {
      "name": "NemesÎs",
      "count": 1
    }
  ],
  "kill_time": {
    "avg": 460614.8,
    "median": 466037.5,
    "p25": 436455.8,
    "p75": 492606.0
  },
  "stats": {},
  "gems": []
}