{
  "season_id": 2,
  "encounter_id": 3183,
  "boss_name": "Midnight Falls",
  "boss_name_cn": "至暗之夜降临",
  "class_name": "Druid",
  "spec_name": "Feral",
  "sample_count": 10,
  "dps": {
    "avg": 103576.3,
    "median": 125776.9,
    "p25": 109782.1,
    "p75": 135632.2,
    "max": 145495.4,
    "min": 6.6,
    "sample_count": 10
  },
  "talents": [
    {
      "build": "ea49ffc7d2c7",
      "count": 1,
      "pct": 10.0,
      "avg_dps": 145495.4
    },
    {
      "build": "93b7d43841a3",
      "count": 1,
      "pct": 10.0,
      "avg_dps": 141427.3
    },
    {
      "build": "e2f972958890",
      "count": 1,
      "pct": 10.0,
      "avg_dps": 137362.7
    },
    {
      "build": "efc212865d77",
      "count": 1,
      "pct": 10.0,
      "avg_dps": 130440.6
    },
    {
      "build": "3ed8b966834a",
      "count": 1,
      "pct": 10.0,
      "avg_dps": 125875.8
    },
    {
      "build": "dc6f6ff5933c",
      "count": 1,
      "pct": 10.0,
      "avg_dps": 125678.0
    },
    {
      "build": "42f8424bd70c",
      "count": 1,
      "pct": 10.0,
      "avg_dps": 124312.4
    },
    {
      "build": "c2989d43da58",
      "count": 1,
      "pct": 10.0,
      "avg_dps": 104938.7
    },
    {
      "build": "55472d422906",
      "count": 1,
      "pct": 10.0,
      "avg_dps": 225.1
    },
    {
      "build": "ba347a509961",
      "count": 1,
      "pct": 10.0,
      "avg_dps": 6.6
    }
  ],
  "gear": {
    "head": [
      {
        "itemID": 250024,
        "name": "Branches of the Luminous Bloom",
        "icon": "inv_helm_leather_raiddruidmidnight_d_01",
        "count": 9,
        "pct": 90.0,
        "avg_itemLevel": 289.0
      }
    ],
    "neck": [
      {
        "itemID": 249368,
        "name": "Eternal Voidsong Chain",
        "icon": "inv_12_jewelry_silvermoonelf_necklace_blue1",
        "count": 3,
        "pct": 30.0,
        "avg_itemLevel": 289.0
      },
      {
        "itemID": 240950,
        "name": "Masterwork Sin'dorei Amulet",
        "icon": "inv_12_profession_jewelcrafting_necklace2_gold",
        "count": 2,
        "pct": 20.0,
        "avg_itemLevel": 285.0
      },
      {
        "itemID": 50228,
        "name": "Barbed Ymirheim Choker",
        "icon": "inv_jewelry_necklace_22",
        "count": 2,
        "pct": 20.0,
        "avg_itemLevel": 282.5
      },
      {
        "itemID": 249337,
        "name": "Ribbon of Coiled Malice",
        "icon": "inv_12_jewelry_devouringhost_necklace_bronze",
        "count": 1,
        "pct": 10.0,
        "avg_itemLevel": 289.0
      },
      {
        "itemID": 251096,
        "name": "Pendant of Aching Grief",
        "icon": "inv_12_jewelry_silvermoonelf_necklace_white",
        "count": 1,
        "pct": 10.0,
        "avg_itemLevel": 289.0
      }
    ],
    "shoulder": [
      {
        "itemID": 250022,
        "name": "Seedpods of the Luminous Bloom",
        "icon": "inv_shoulder_leather_raiddruidmidnight_d_01",
        "count": 8,
        "pct": 80.0,
        "avg_itemLevel": 287.4
      },
      {
        "itemID": 251092,
        "name": "Fallen Grunt's Mantle",
        "icon": "inv_shoulder_leather_dungeonharronir_c_01",
        "count": 1,
        "pct": 10.0,
        "avg_itemLevel": 289.0
      }
    ],
    "shirt": [
      {
        "itemID": 268274,
        "name": "Blinky's Collar",
        "icon": "inv_jewelry_necklace_22",
        "count": 3,
        "pct": 30.0,
        "avg_itemLevel": 1.0
      },
      {
        "itemID": 250027,
        "name": "Trunk of the Luminous Bloom",
        "icon": "inv_chest_leather_raiddruidmidnight_d_01",
        "count": 2,
        "pct": 20.0,
        "avg_itemLevel": 289.0
      },
      {
        "itemID": 167082,
        "name": "Stylish Black Shirt",
        "icon": "inv_shirt_black_01",
        "count": 1,
        "pct": 10.0,
        "avg_itemLevel": 1.0
      },
      {
        "itemID": 52019,
        "name": "Precious's Ribbon",
        "icon": "inv_misc_ribbon_01",
        "count": 1,
        "pct": 10.0,
        "avg_itemLevel": 1.0
      },
      {
        "itemID": 4336,
        "name": "Black Swashbuckler's Shirt",
        "icon": "inv_shirt_black_01",
        "count": 1,
        "pct": 10.0,
        "avg_itemLevel": 1.0
      },
      {
        "itemID": 244570,
        "name": "Silvermoon Agent's Coat",
        "icon": "inv_chest_leather_questbloodelf_b_01",
        "count": 1,
        "pct": 10.0,
        "avg_itemLevel": 285.0
      }
    ],
    "chest": [
      {
        "itemID": 250027,
        "name": "Trunk of the Luminous Bloom",
        "icon": "inv_chest_leather_raiddruidmidnight_d_01",
        "count": 4,
        "pct": 40.0,
        "avg_itemLevel": 285.8
      },
      {
        "itemID": 249374,
        "name": "Scorn-Scarred Shul'ka's Belt",
        "icon": "inv_belt_leather_raidmonkmidnight_d_01",
        "count": 2,
        "pct": 20.0,
        "avg_itemLevel": 289.0
      },
      {
        "itemID": 251166,
        "name": "Falconer's Cinch",
        "icon": "inv_belt_leather_dungeonharronir_c_01",
        "count": 1,
        "pct": 10.0,
        "avg_itemLevel": 289.0
      },
      {
        "itemID": 251216,
        "name": "Maledict Vest",
        "icon": "inv_chest_leather_dungeonharronir_c_01",
        "count": 1,
        "pct": 10.0,
        "avg_itemLevel": 289.0
      },
      {
        "itemID": 244570,
        "name": "Silvermoon Agent's Coat",
        "icon": "inv_chest_leather_questbloodelf_b_01",
        "count": 1,
        "pct": 10.0,
        "avg_itemLevel": 285.0
      }
    ],
    "waist": [
      {
        "itemID": 251082,
        "name": "Snapvine Cinch",
        "icon": "inv_belt_leather_dungeonharronir_c_01",
        "count": 3,
        "pct": 30.0,
        "avg_itemLevel": 289.0
      },
      {
        "itemID": 250023,
        "name": "Phloemwraps of the Luminous Bloom",
        "icon": "inv_pant_leather_raiddruidmidnight_d_01",
        "count": 2,
        "pct": 20.0,
        "avg_itemLevel": 289.0
      },
      {
        "itemID": 249374,
        "name": "Scorn-Scarred Shul'ka's Belt",
        "icon": "inv_belt_leather_raidmonkmidnight_d_01",
        "count": 1,
        "pct": 10.0,
        "avg_itemLevel": 289.0
      },
      {
        "itemID": 49817,
        "name": "Shaggy Wyrmleather Leggings",
        "icon": "inv_pants_leather_30a",
        "count": 1,
        "pct": 10.0,
        "avg_itemLevel": 289.0
      },
      {
        "itemID": 250021,
        "name": "Barksash of the Luminous Bloom",
        "icon": "inv_belt_leather_raiddruidmidnight_d_01",
        "count": 1,
        "pct": 10.0,
        "avg_itemLevel": 289.0
      },
      {
        "itemID": 249314,
        "name": "Twisted Twilight Sash",
        "icon": "inv_belt_leather_raiddemonhuntermidnight_d_01",
        "count": 1,
        "pct": 10.0,
        "avg_itemLevel": 289.0
      }
    ],
    "legs": [
      {
        "itemID": 250023,
        "name": "Phloemwraps of the Luminous Bloom",
        "icon": "inv_pant_leather_raiddruidmidnight_d_01",
        "count": 6,
        "pct": 60.0,
        "avg_itemLevel": 284.7
      },
      {
        "itemID": 251121,
        "name": "Domanaar's Dire Treads",
        "icon": "inv_boot_leather_dungeonharronir_c_01",
        "count": 1,
        "pct": 10.0,
        "avg_itemLevel": 289.0
      },
      {
        "itemID": 244569,
        "name": "Silvermoon Agent's Sneakers",
        "icon": "inv_boot_leather_questbloodelf_b_01",
        "count": 1,
        "pct": 10.0,
        "avg_itemLevel": 285.0
      },
      {
        "itemID": 249334,
        "name": "Void-Claimed Shinkickers",
        "icon": "inv_boot_leather_raiddemonhuntermidnight_d_01",
        "count": 1,
        "pct": 10.0,
        "avg_itemLevel": 289.0
      }
    ],
    "feet": [
      {
        "itemID": 250026,
        "name": "Rootslippers of the Luminous Bloom",
        "icon": "inv_boot_leather_raiddruidmidnight_d_01",
        "count": 4,
        "pct": 40.0,
        "avg_itemLevel": 289.0
      },
      {
        "itemID": 244576,
        "name": "Silvermoon Agent's Deflectors",
        "icon": "inv_bracer_leather_questbloodelf_b_01",
        "count": 3,
        "pct": 30.0,
        "avg_itemLevel": 285.0
      },
      {
        "itemID": 244569,
        "name": "Silvermoon Agent's Sneakers",
        "icon": "inv_boot_leather_questbloodelf_b_01",
        "count": 1,
        "pct": 10.0,
        "avg_itemLevel": 285.0
      },
      {
        "itemID": 260372,
        "name": "Nullstrider's Boots",
        "icon": "inv_boot_leather_raidroguemidnight_d_01",
        "count": 1,
        "pct": 10.0,
        "avg_itemLevel": 289.0
      }
    ],
    "wrist": [
      {
        "itemID": 244576,
        "name": "Silvermoon Agent's Deflectors",
        "icon": "inv_bracer_leather_questbloodelf_b_01",
        "count": 5,
        "pct": 50.0,
        "avg_itemLevel": 285.0
      },
      {
        "itemID": 250025,
        "name": "Arbortenders of the Luminous Bloom",
        "icon": "inv_glove_leather_raiddruidmidnight_d_01",
        "count": 3,
        "pct": 30.0,
        "avg_itemLevel": 289.0
      },
      {
        "itemID": 50264,
        "name": "Chewed Leather Wristguards",
        "icon": "inv_bracer_23a",
        "count": 1,
        "pct": 10.0,
        "avg_itemLevel": 289.0
      }
    ],
    "hands": [
      {
        "itemID": 250025,
        "name": "Arbortenders of the Luminous Bloom",
        "icon": "inv_glove_leather_raiddruidmidnight_d_01",
        "count": 5,
        "pct": 50.0,
        "avg_itemLevel": 289.0
      },
      {
        "itemID": 251093,
        "name": "Omission of Light",
        "icon": "inv_12_trinket_devouring_host_currency1_silver",
        "count": 2,
        "pct": 20.0,
        "avg_itemLevel": 289.0
      },
      {
        "itemID": 249321,
        "name": "Vaelgor's Fearsome Grasp",
        "icon": "inv_glove_leather_raiddruidmidnight_d_01",
        "count": 1,
        "pct": 10.0,
        "avg_itemLevel": 289.0
      },
      {
        "itemID": 249919,
        "name": "Sin'dorei Band of Hope",
        "icon": "inv_12_jewelry_silvermoonelf_ring_red1",
        "count": 1,
        "pct": 10.0,
        "avg_itemLevel": 289.0
      }
    ],
    "finger1": [
      {
        "itemID": 251217,
        "name": "Occlusion of Void",
        "icon": "inv_12_trinket_devouring_host_currency1_bronze",
        "count": 5,
        "pct": 50.0,
        "avg_itemLevel": 289.0
      },
      {
        "itemID": 251093,
        "name": "Omission of Light",
        "icon": "inv_12_trinket_devouring_host_currency1_silver",
        "count": 4,
        "pct": 40.0,
        "avg_itemLevel": 289.0
      }
    ],
    "finger2": [
      {
        "itemID": 251217,
        "name": "Occlusion of Void",
        "icon": "inv_12_trinket_devouring_host_currency1_bronze",
        "count": 3,
        "pct": 30.0,
        "avg_itemLevel": 284.7
      },
      {
        "itemID": 193701,
        "name": "Algeth'ar Puzzle Box",
        "icon": "inv_misc_enggizmos_18",
        "count": 2,
        "pct": 20.0,
        "avg_itemLevel": 291.5
      },
      {
        "itemID": 251093,
        "name": "Omission of Light",
        "icon": "inv_12_trinket_devouring_host_currency1_silver",
        "count": 2,
        "pct": 20.0,
        "avg_itemLevel": 289.0
      },
      {
        "itemID": 193708,
        "name": "Platinum Star Band",
        "icon": "inv_10_dungeonjewelry_explorer_ring_1_color1",
        "count": 1,
        "pct": 10.0,
        "avg_itemLevel": 289.0
      },
      {
        "itemID": 249343,
        "name": "Gaze of the Alnseer",
        "icon": "inv_12_trinket_raid_dreamrift_gazeofthealnseer",
        "count": 1,
        "pct": 10.0,
        "avg_itemLevel": 298.0
      }
    ],
    "trinket1": [
      {
        "itemID": 193701,
        "name": "Algeth'ar Puzzle Box",
        "icon": "inv_misc_enggizmos_18",
        "count": 6,
        "pct": 60.0,
        "avg_itemLevel": 295.8
      },
      {
        "itemID": 249343,
        "name": "Gaze of the Alnseer",
        "icon": "inv_12_trinket_raid_dreamrift_gazeofthealnseer",
        "count": 3,
        "pct": 30.0,
        "avg_itemLevel": 298.0
      }
    ],
    "trinket2": [
      {
        "itemID": 249343,
        "name": "Gaze of the Alnseer",
        "icon": "inv_12_trinket_raid_dreamrift_gazeofthealnseer",
        "count": 5,
        "pct": 50.0,
        "avg_itemLevel": 298.0
      },
      {
        "itemID": 239656,
        "name": "Adherent's Silken Shroud",
        "icon": "inv_cape_cloth_questbloodelf_b_01",
        "count": 1,
        "pct": 10.0,
        "avg_itemLevel": 285.0
      },
      {
        "itemID": 249370,
        "name": "Draconic Nullcape",
        "icon": "inv_plate_revendrethraid_d_01_cape",
        "count": 1,
        "pct": 10.0,
        "avg_itemLevel": 289.0
      },
      {
        "itemID": 193701,
        "name": "Algeth'ar Puzzle Box",
        "icon": "inv_misc_enggizmos_18",
        "count": 1,
        "pct": 10.0,
        "avg_itemLevel": 298.0
      },
      {
        "itemID": 250019,
        "name": "Leafdrape of the Luminous Bloom",
        "icon": "inv_cape_leather_raiddruidmidnight_d_01",
        "count": 1,
        "pct": 10.0,
        "avg_itemLevel": 289.0
      }
    ],
    "back": [
      {
        "itemID": 239656,
        "name": "Adherent's Silken Shroud",
        "icon": "inv_cape_cloth_questbloodelf_b_01",
        "count": 4,
        "pct": 40.0,
        "avg_itemLevel": 285.0
      },
      {
        "itemID": 258529,
        "name": "Arcaneclaw Spear",
        "icon": "inv_polearm_2h_dragondungeon_c_01",
        "count": 3,
        "pct": 30.0,
        "avg_itemLevel": 298.0
      },
      {
        "itemID": 249335,
        "name": "Imperator's Banner",
        "icon": "inv_plate_raiddeathknightmidnight_d_01_cape",
        "count": 1,
        "pct": 10.0,
        "avg_itemLevel": 289.0
      },
      {
        "itemID": 249370,
        "name": "Draconic Nullcape",
        "icon": "inv_plate_revendrethraid_d_01_cape",
        "count": 1,
        "pct": 10.0,
        "avg_itemLevel": 289.0
      }
    ],
    "main_hand": [
      {
        "itemID": 249302,
        "name": "Inescapable Reach",
        "icon": "inv_polearm_2h_raidmidnight_d_01",
        "count": 4,
        "pct": 40.0,
        "avg_itemLevel": 298.0
      },
      {
        "itemID": 210501,
        "name": "Dream Wardens Tabard",
        "icon": "inv_tabard_denizens_b_01",
        "count": 1,
        "pct": 10.0,
        "avg_itemLevel": 1.0
      },
      {
        "itemID": 258529,
        "name": "Arcaneclaw Spear",
        "icon": "inv_polearm_2h_dragondungeon_c_01",
        "count": 1,
        "pct": 10.0,
        "avg_itemLevel": 298.0
      },
      {
        "itemID": 249278,
        "name": "Alnscorned Spire",
        "icon": "inv_staff_2h_raidmidnight_d_01",
        "count": 1,
        "pct": 10.0,
        "avg_itemLevel": 298.0
      }
    ],
    "off_hand": [
      {
        "itemID": 5976,
        "name": "Guild Tabard",
        "icon": "inv_shirt_guildtabard_01",
        "count": 2,
        "pct": 20.0,
        "avg_itemLevel": 1.0
      },
      {
        "itemID": 69210,
        "name": "Renowned Guild Tabard",
        "icon": "inv_epicguildtabard",
        "count": 1,
        "pct": 10.0,
        "avg_itemLevel": 1.0
      }
    ]
  },
  "race": {},
  "factions": {
    "alliance": 6,
    "horde": 4
  },
  "guilds": [
    {
      "name": "Do Over",
      "count": 1
    },
    {
      "name": "Bad End",
      "count": 1
    },
    {
      "name": "Resonance",
      "count": 1
    },
    {
      "name": "Internet Friends",
      "count": 1
    },
    {
      "name": "A Necessary Evil",
      "count": 1
    },
    {
      "name": "Vestige",
      "count": 1
    },
    {
      "name": "Nascent",
      "count": 1
    }
  ],
  "kill_time": {
    "avg": 532109.6,
    "median": 532374.5,
    "p25": 524287.2,
    "p75": 537563.8
  },
  "stats": {},
  "gems": []
}