{
  "season_id": 2,
  "encounter_id": 3180,
  "boss_name": "Lightblinded Vanguard",
  "boss_name_cn": "战争牧师瑟恩",
  "class_name": "DemonHunter",
  "spec_name": "Havoc",
  "sample_count": 26,
  "dps": {
    "avg": 173994.9,
    "median": 183508.6,
    "p25": 160251.9,
    "p75": 192949.3,
    "max": 215707.8,
    "min": 115407.3,
    "sample_count": 26
  },
  "talents": [
    {
      "build": "d5e759c97f16",
      "count": 4,
      "pct": 15.4,
      "avg_dps": 187082.1
    },
    {
      "build": "3f227e72662d",
      "count": 2,
      "pct": 7.7,
      "avg_dps": 165557.6
    },
    {
      "build": "439788408a24",
      "count": 2,
      "pct": 7.7,
      "avg_dps": 190838.5
    },
    {
      "build": "4c524b9d5988",
      "count": 1,
      "pct": 3.8,
      "avg_dps": 204091.6
    },
    {
      "build": "163559537fa8",
      "count": 1,
      "pct": 3.8,
      "avg_dps": 203259.2
    },
    {
      "build": "fb6b4e4a02e7",
      "count": 1,
      "pct": 3.8,
      "avg_dps": 196674.0
    },
    {
      "build": "40f627ffb419",
      "count": 1,
      "pct": 3.8,
      "avg_dps": 193589.6
    },
    {
      "build": "a98bd13ab1d7",
      "count": 1,
      "pct": 3.8,
      "avg_dps": 189245.9
    },
    {
      "build": "d5d09bf89185",
      "count": 1,
      "pct": 3.8,
      "avg_dps": 184987.5
    },
    {
      "build": "c0b4ce0bc935",
      "count": 1,
      "pct": 3.8,
      "avg_dps": 184876.0
    },
    {
      "build": "bd7ff57295ff",
      "count": 1,
      "pct": 3.8,
      "avg_dps": 184345.5
    },
    {
      "build": "d0031708035d",
      "count": 1,
      "pct": 3.8,
      "avg_dps": 179539.0
    },
    {
      "build": "790a6d2b8c3f",
      "count": 1,
      "pct": 3.8,
      "avg_dps": 165656.4
    },
    {
      "build": "6dca1582bfc8",
      "count": 1,
      "pct": 3.8,
      "avg_dps": 165338.3
    },
    {
      "build": "a1e43fc013d7",
      "count": 1,
      "pct": 3.8,
      "avg_dps": 164440.3
    },
    {
      "build": "e4a89442f7c7",
      "count": 1,
      "pct": 3.8,
      "avg_dps": 159988.4
    },
    {
      "build": "7125647da116",
      "count": 1,
      "pct": 3.8,
      "avg_dps": 152812.0
    },
    {
      "build": "aa6001626ea8",
      "count": 1,
      "pct": 3.8,
      "avg_dps": 149737.8
    },
    {
      "build": "e7415aeacaeb",
      "count": 1,
      "pct": 3.8,
      "avg_dps": 134559.8
    },
    {
      "build": "32584a6cec4b",
      "count": 1,
      "pct": 3.8,
      "avg_dps": 132957.7
    }
  ],
  "gear": {
    "head": [
      {
        "itemID": 250033,
        "name": "Devouring Reaver's Intake",
        "icon": "inv_helm_leather_raiddemonhuntermidnight_d_01",
        "count": 21,
        "pct": 80.8,
        "avg_itemLevel": 290.3
      },
      {
        "itemID": 249306,
        "name": "Devouring Night's Visage",
        "icon": "inv_helm_leather_raiddemonhuntermidnight_d_01",
        "count": 4,
        "pct": 15.4,
        "avg_itemLevel": 285.8
      },
      {
        "itemID": 251109,
        "name": "Spellsnap Shadowmask",
        "icon": "inv_helm_leather_dungeonharronir_c_01",
        "count": 1,
        "pct": 3.8,
        "avg_itemLevel": 289.0
      }
    ],
    "neck": [
      {
        "itemID": 240950,
        "name": "Masterwork Sin'dorei Amulet",
        "icon": "inv_12_profession_jewelcrafting_necklace2_gold",
        "count": 11,
        "pct": 42.3,
        "avg_itemLevel": 285.0
      },
      {
        "itemID": 268291,
        "name": "Rotmire's Sporeheart",
        "icon": "inv_12_jewelry_rutaani_necklace_blue",
        "count": 5,
        "pct": 19.2,
        "avg_itemLevel": 298.0
      },
      {
        "itemID": 249337,
        "name": "Ribbon of Coiled Malice",
        "icon": "inv_12_jewelry_devouringhost_necklace_bronze",
        "count": 3,
        "pct": 11.5,
        "avg_itemLevel": 289.0
      },
      {
        "itemID": 249368,
        "name": "Eternal Voidsong Chain",
        "icon": "inv_12_jewelry_silvermoonelf_necklace_blue1",
        "count": 2,
        "pct": 7.7,
        "avg_itemLevel": 289.0
      },
      {
        "itemID": 250247,
        "name": "Amulet of the Abyssal Hymn",
        "icon": "inv_12_jewelry_devouringhost_necklace_bronze2",
        "count": 2,
        "pct": 7.7,
        "avg_itemLevel": 289.0
      },
      {
        "itemID": 50228,
        "name": "Barbed Ymirheim Choker",
        "icon": "inv_jewelry_necklace_22",
        "count": 2,
        "pct": 7.7,
        "avg_itemLevel": 274.0
      },
      {
        "itemID": 251096,
        "name": "Pendant of Aching Grief",
        "icon": "inv_12_jewelry_silvermoonelf_necklace_white",
        "count": 1,
        "pct": 3.8,
        "avg_itemLevel": 276.0
      }
    ],
    "shoulder": [
      {
        "itemID": 250031,
        "name": "Devouring Reaver's Exhaustplates",
        "icon": "inv_shoulder_leather_raiddemonhuntermidnight_d_01",
        "count": 26,
        "pct": 100.0,
        "avg_itemLevel": 287.6
      }
    ],
    "shirt": [
      {
        "itemID": 250036,
        "name": "Devouring Reaver's Engine",
        "icon": "inv_chest_leather_raiddemonhuntermidnight_d_01",
        "count": 9,
        "pct": 34.6,
        "avg_itemLevel": 287.6
      },
      {
        "itemID": 268274,
        "name": "Blinky's Collar",
        "icon": "inv_jewelry_necklace_22",
        "count": 8,
        "pct": 30.8,
        "avg_itemLevel": 1.0
      },
      {
        "itemID": 89195,
        "name": "Artisan Officer's Shirt",
        "icon": "inv_shirt03_epic",
        "count": 2,
        "pct": 7.7,
        "avg_itemLevel": 1.0
      },
      {
        "itemID": 14617,
        "name": "Sawbones Shirt",
        "icon": "inv_shirt_red_01",
        "count": 1,
        "pct": 3.8,
        "avg_itemLevel": 1.0
      },
      {
        "itemID": 98543,
        "name": "Wraps of the Blood-Soaked Brawler",
        "icon": "inv_chest_leather_20",
        "count": 1,
        "pct": 3.8,
        "avg_itemLevel": 1.0
      },
      {
        "itemID": 4333,
        "name": "Dark Silk Shirt",
        "icon": "inv_shirt_black_01",
        "count": 1,
        "pct": 3.8,
        "avg_itemLevel": 1.0
      },
      {
        "itemID": 10052,
        "name": "Orange Martial Shirt",
        "icon": "inv_shirt_orange_01",
        "count": 1,
        "pct": 3.8,
        "avg_itemLevel": 1.0
      },
      {
        "itemID": 41253,
        "name": "Blue Workman's Shirt",
        "icon": "inv_shirt_13",
        "count": 1,
        "pct": 3.8,
        "avg_itemLevel": 1.0
      },
      {
        "itemID": 167194,
        "name": "Purple Martial Shirt",
        "icon": "inv_shirt_purple_01",
        "count": 1,
        "pct": 3.8,
        "avg_itemLevel": 1.0
      },
      {
        "itemID": 167185,
        "name": "Ebon Filigreed Shirt",
        "icon": "inv_shirt_black_01",
        "count": 1,
        "pct": 3.8,
        "avg_itemLevel": 1.0
      }
    ],
    "chest": [
      {
        "itemID": 250036,
        "name": "Devouring Reaver's Engine",
        "icon": "inv_chest_leather_raiddemonhuntermidnight_d_01",
        "count": 17,
        "pct": 65.4,
        "avg_itemLevel": 287.6
      },
      {
        "itemID": 244573,
        "name": "Silvermoon Agent's Utility Belt",
        "icon": "inv_belt_leather_questbloodelf_b_01",
        "count": 4,
        "pct": 15.4,
        "avg_itemLevel": 285.0
      },
      {
        "itemID": 251082,
        "name": "Snapvine Cinch",
        "icon": "inv_belt_leather_dungeonharronir_c_01",
        "count": 2,
        "pct": 7.7,
        "avg_itemLevel": 289.0
      },
      {
        "itemID": 250030,
        "name": "Devouring Reaver's Emblem",
        "icon": "inv_belt_leather_raiddemonhuntermidnight_d_01",
        "count": 1,
        "pct": 3.8,
        "avg_itemLevel": 298.0
      },
      {
        "itemID": 249374,
        "name": "Scorn-Scarred Shul'ka's Belt",
        "icon": "inv_belt_leather_raidmonkmidnight_d_01",
        "count": 1,
        "pct": 3.8,
        "avg_itemLevel": 289.0
      },
      {
        "itemID": 249314,
        "name": "Twisted Twilight Sash",
        "icon": "inv_belt_leather_raiddemonhuntermidnight_d_01",
        "count": 1,
        "pct": 3.8,
        "avg_itemLevel": 276.0
      }
    ],
    "waist": [
      {
        "itemID": 251082,
        "name": "Snapvine Cinch",
        "icon": "inv_belt_leather_dungeonharronir_c_01",
        "count": 5,
        "pct": 19.2,
        "avg_itemLevel": 289.0
      },
      {
        "itemID": 250032,
        "name": "Devouring Reaver's Pistons",
        "icon": "inv_pant_leather_raiddemonhuntermidnight_d_01",
        "count": 5,
        "pct": 19.2,
        "avg_itemLevel": 286.4
      },
      {
        "itemID": 250030,
        "name": "Devouring Reaver's Emblem",
        "icon": "inv_belt_leather_raiddemonhuntermidnight_d_01",
        "count": 4,
        "pct": 15.4,
        "avg_itemLevel": 289.0
      },
      {
        "itemID": 244573,
        "name": "Silvermoon Agent's Utility Belt",
        "icon": "inv_belt_leather_questbloodelf_b_01",
        "count": 4,
        "pct": 15.4,
        "avg_itemLevel": 285.0
      },
      {
        "itemID": 244574,
        "name": "Silvermoon Agent's Leggings",
        "icon": "inv_pant_leather_questbloodelf_b_01",
        "count": 3,
        "pct": 11.5,
        "avg_itemLevel": 285.0
      },
      {
        "itemID": 260373,
        "name": "Power Stance Breeches",
        "icon": "inv_pant_leather_raidmonkmidnight_d_01",
        "count": 1,
        "pct": 3.8,
        "avg_itemLevel": 289.0
      },
      {
        "itemID": 268286,
        "name": "Sash of the Putrid Giant",
        "icon": "inv_belt_leather_raidroguemidnight_d_01",
        "count": 1,
        "pct": 3.8,
        "avg_itemLevel": 298.0
      },
      {
        "itemID": 49806,
        "name": "Flayer's Black Belt",
        "icon": "inv_belt_65",
        "count": 1,
        "pct": 3.8,
        "avg_itemLevel": 289.0
      },
      {
        "itemID": 249314,
        "name": "Twisted Twilight Sash",
        "icon": "inv_belt_leather_raiddemonhuntermidnight_d_01",
        "count": 1,
        "pct": 3.8,
        "avg_itemLevel": 289.0
      },
      {
        "itemID": 245964,
        "name": "Durable Information Securing Container",
        "icon": "inv_armor_waistoftime_d_01_belt_titan-copy",
        "count": 1,
        "pct": 3.8,
        "avg_itemLevel": 141.0
      }
    ],
    "legs": [
      {
        "itemID": 250035,
        "name": "Devouring Reaver's Soul Flatteners",
        "icon": "inv_boot_leather_raiddemonhuntermidnight_d_01",
        "count": 7,
        "pct": 26.9,
        "avg_itemLevel": 289.0
      },
      {
        "itemID": 260373,
        "name": "Power Stance Breeches",
        "icon": "inv_pant_leather_raidmonkmidnight_d_01",
        "count": 6,
        "pct": 23.1,
        "avg_itemLevel": 289.0
      },
      {
        "itemID": 244574,
        "name": "Silvermoon Agent's Leggings",
        "icon": "inv_pant_leather_questbloodelf_b_01",
        "count": 4,
        "pct": 15.4,
        "avg_itemLevel": 285.0
      },
      {
        "itemID": 250032,
        "name": "Devouring Reaver's Pistons",
        "icon": "inv_pant_leather_raiddemonhuntermidnight_d_01",
        "count": 4,
        "pct": 15.4,
        "avg_itemLevel": 289.0
      },
      {
        "itemID": 258577,
        "name": "Boots of Burning Focus",
        "icon": "inv_leather_draenordungeon_c_01boot",
        "count": 2,
        "pct": 7.7,
        "avg_itemLevel": 289.0
      },
      {
        "itemID": 251087,
        "name": "Legwraps of Lingering Legacies",
        "icon": "inv_pant_leather_dungeonharronir_c_01",
        "count": 2,
        "pct": 7.7,
        "avg_itemLevel": 280.5
      },
      {
        "itemID": 249312,
        "name": "Nightblade's Pantaloons",
        "icon": "inv_pant_leather_raidroguemidnight_d_01",
        "count": 1,
        "pct": 3.8,
        "avg_itemLevel": 289.0
      }
    ],
    "feet": [
      {
        "itemID": 250035,
        "name": "Devouring Reaver's Soul Flatteners",
        "icon": "inv_boot_leather_raiddemonhuntermidnight_d_01",
        "count": 10,
        "pct": 38.5,
        "avg_itemLevel": 289.0
      },
      {
        "itemID": 244576,
        "name": "Silvermoon Agent's Deflectors",
        "icon": "inv_bracer_leather_questbloodelf_b_01",
        "count": 5,
        "pct": 19.2,
        "avg_itemLevel": 285.0
      },
      {
        "itemID": 258577,
        "name": "Boots of Burning Focus",
        "icon": "inv_leather_draenordungeon_c_01boot",
        "count": 4,
        "pct": 15.4,
        "avg_itemLevel": 284.8
      },
      {
        "itemID": 249327,
        "name": "Void-Skinned Bracers",
        "icon": "inv_bracer_leather_raidroguemidnight_d_01",
        "count": 2,
        "pct": 7.7,
        "avg_itemLevel": 282.5
      },
      {
        "itemID": 249382,
        "name": "Canopy Walker's Footwraps",
        "icon": "inv_boot_leather_raiddruidmidnight_d_01",
        "count": 2,
        "pct": 7.7,
        "avg_itemLevel": 289.0
      },
      {
        "itemID": 250029,
        "name": "Devouring Reaver's Support Straps",
        "icon": "inv_bracer_leather_raiddemonhuntermidnight_d_01",
        "count": 1,
        "pct": 3.8,
        "avg_itemLevel": 289.0
      },
      {
        "itemID": 260372,
        "name": "Nullstrider's Boots",
        "icon": "inv_boot_leather_raidroguemidnight_d_01",
        "count": 1,
        "pct": 3.8,
        "avg_itemLevel": 276.0
      },
      {
        "itemID": 50264,
        "name": "Chewed Leather Wristguards",
        "icon": "inv_bracer_23a",
        "count": 1,
        "pct": 3.8,
        "avg_itemLevel": 276.0
      }
    ],
    "wrist": [
      {
        "itemID": 244576,
        "name": "Silvermoon Agent's Deflectors",
        "icon": "inv_bracer_leather_questbloodelf_b_01",
        "count": 9,
        "pct": 34.6,
        "avg_itemLevel": 285.0
      },
      {
        "itemID": 250034,
        "name": "Devouring Reaver's Essence Grips",
        "icon": "inv_glove_leather_raiddemonhuntermidnight_d_01",
        "count": 9,
        "pct": 34.6,
        "avg_itemLevel": 287.6
      },
      {
        "itemID": 250029,
        "name": "Devouring Reaver's Support Straps",
        "icon": "inv_bracer_leather_raiddemonhuntermidnight_d_01",
        "count": 3,
        "pct": 11.5,
        "avg_itemLevel": 289.0
      },
      {
        "itemID": 193714,
        "name": "Frenzyroot Cuffs",
        "icon": "inv_leather_dragondungeon_c_01_bracer",
        "count": 3,
        "pct": 11.5,
        "avg_itemLevel": 283.3
      },
      {
        "itemID": 249327,
        "name": "Void-Skinned Bracers",
        "icon": "inv_bracer_leather_raidroguemidnight_d_01",
        "count": 2,
        "pct": 7.7,
        "avg_itemLevel": 289.0
      }
    ],
    "hands": [
      {
        "itemID": 250034,
        "name": "Devouring Reaver's Essence Grips",
        "icon": "inv_glove_leather_raiddemonhuntermidnight_d_01",
        "count": 17,
        "pct": 65.4,
        "avg_itemLevel": 288.0
      },
      {
        "itemID": 193708,
        "name": "Platinum Star Band",
        "icon": "inv_10_dungeonjewelry_explorer_ring_1_color1",
        "count": 4,
        "pct": 15.4,
        "avg_itemLevel": 289.0
      },
      {
        "itemID": 251093,
        "name": "Omission of Light",
        "icon": "inv_12_trinket_devouring_host_currency1_silver",
        "count": 1,
        "pct": 3.8,
        "avg_itemLevel": 289.0
      },
      {
        "itemID": 249336,
        "name": "Signet of the Starved Beast",
        "icon": "inv_12_jewelry_devouringhost_ring_silver2",
        "count": 1,
        "pct": 3.8,
        "avg_itemLevel": 289.0
      },
      {
        "itemID": 249919,
        "name": "Sin'dorei Band of Hope",
        "icon": "inv_12_jewelry_silvermoonelf_ring_red1",
        "count": 1,
        "pct": 3.8,
        "avg_itemLevel": 276.0
      },
      {
        "itemID": 251217,
        "name": "Occlusion of Void",
        "icon": "inv_12_trinket_devouring_host_currency1_bronze",
        "count": 1,
        "pct": 3.8,
        "avg_itemLevel": 289.0
      },
      {
        "itemID": 268290,
        "name": "Sporecaller's Blooming Loop",
        "icon": "inv_12_jewelry_rutaani_ring_blue",
        "count": 1,
        "pct": 3.8,
        "avg_itemLevel": 298.0
      }
    ],
    "finger1": [
      {
        "itemID": 193708,
        "name": "Platinum Star Band",
        "icon": "inv_10_dungeonjewelry_explorer_ring_1_color1",
        "count": 11,
        "pct": 42.3,
        "avg_itemLevel": 287.8
      },
      {
        "itemID": 240949,
        "name": "Masterwork Sin'dorei Band",
        "icon": "inv_12_profession_jewelcrafting_ring4_gold",
        "count": 6,
        "pct": 23.1,
        "avg_itemLevel": 285.0
      },
      {
        "itemID": 249919,
        "name": "Sin'dorei Band of Hope",
        "icon": "inv_12_jewelry_silvermoonelf_ring_red1",
        "count": 4,
        "pct": 15.4,
        "avg_itemLevel": 289.0
      },
      {
        "itemID": 251513,
        "name": "Loa Worshiper's Band",
        "icon": "inv_12_profession_jewelcrafting_ring3_silver",
        "count": 2,
        "pct": 7.7,
        "avg_itemLevel": 285.0
      },
      {
        "itemID": 251217,
        "name": "Occlusion of Void",
        "icon": "inv_12_trinket_devouring_host_currency1_bronze",
        "count": 1,
        "pct": 3.8,
        "avg_itemLevel": 289.0
      },
      {
        "itemID": 49812,
        "name": "Purloined Wedding Ring",
        "icon": "inv_jewelry_ring_42",
        "count": 1,
        "pct": 3.8,
        "avg_itemLevel": 266.0
      },
      {
        "itemID": 151308,
        "name": "Eredath Seal of Nobility",
        "icon": "inv_70_dungeon_ring3c",
        "count": 1,
        "pct": 3.8,
        "avg_itemLevel": 289.0
      }
    ],
    "finger2": [
      {
        "itemID": 193708,
        "name": "Platinum Star Band",
        "icon": "inv_10_dungeonjewelry_explorer_ring_1_color1",
        "count": 7,
        "pct": 26.9,
        "avg_itemLevel": 287.1
      },
      {
        "itemID": 249919,
        "name": "Sin'dorei Band of Hope",
        "icon": "inv_12_jewelry_silvermoonelf_ring_red1",
        "count": 6,
        "pct": 23.1,
        "avg_itemLevel": 289.0
      },
      {
        "itemID": 249343,
        "name": "Gaze of the Alnseer",
        "icon": "inv_12_trinket_raid_dreamrift_gazeofthealnseer",
        "count": 6,
        "pct": 23.1,
        "avg_itemLevel": 298.0
      },
      {
        "itemID": 193701,
        "name": "Algeth'ar Puzzle Box",
        "icon": "inv_misc_enggizmos_18",
        "count": 3,
        "pct": 11.5,
        "avg_itemLevel": 298.0
      },
      {
        "itemID": 240949,
        "name": "Masterwork Sin'dorei Band",
        "icon": "inv_12_profession_jewelcrafting_ring4_gold",
        "count": 2,
        "pct": 7.7,
        "avg_itemLevel": 285.0
      },
      {
        "itemID": 251217,
        "name": "Occlusion of Void",
        "icon": "inv_12_trinket_devouring_host_currency1_bronze",
        "count": 1,
        "pct": 3.8,
        "avg_itemLevel": 289.0
      },
      {
        "itemID": 251093,
        "name": "Omission of Light",
        "icon": "inv_12_trinket_devouring_host_currency1_silver",
        "count": 1,
        "pct": 3.8,
        "avg_itemLevel": 266.0
      }
    ],
    "trinket1": [
      {
        "itemID": 193701,
        "name": "Algeth'ar Puzzle Box",
        "icon": "inv_misc_enggizmos_18",
        "count": 16,
        "pct": 61.5,
        "avg_itemLevel": 298.0
      },
      {
        "itemID": 249343,
        "name": "Gaze of the Alnseer",
        "icon": "inv_12_trinket_raid_dreamrift_gazeofthealnseer",
        "count": 7,
        "pct": 26.9,
        "avg_itemLevel": 298.0
      },
      {
        "itemID": 249345,
        "name": "Ranger-Captain's Iridescent Insignia",
        "icon": "inv_12_trinket_raid_voidspire_agidps_rangercaptainsinsignia",
        "count": 1,
        "pct": 3.8,
        "avg_itemLevel": 289.0
      },
      {
        "itemID": 249806,
        "name": "Radiant Plume",
        "icon": "inv_12_dualityphoenix_holy_feather",
        "count": 1,
        "pct": 3.8,
        "avg_itemLevel": 276.0
      },
      {
        "itemID": 250144,
        "name": "Emberwing Feather",
        "icon": "inv_icon_feather06a",
        "count": 1,
        "pct": 3.8,
        "avg_itemLevel": 272.0
      }
    ],
    "trinket2": [
      {
        "itemID": 249343,
        "name": "Gaze of the Alnseer",
        "icon": "inv_12_trinket_raid_dreamrift_gazeofthealnseer",
        "count": 13,
        "pct": 50.0,
        "avg_itemLevel": 298.0
      },
      {
        "itemID": 193701,
        "name": "Algeth'ar Puzzle Box",
        "icon": "inv_misc_enggizmos_18",
        "count": 4,
        "pct": 15.4,
        "avg_itemLevel": 298.0
      },
      {
        "itemID": 249335,
        "name": "Imperator's Banner",
        "icon": "inv_plate_raiddeathknightmidnight_d_01_cape",
        "count": 3,
        "pct": 11.5,
        "avg_itemLevel": 289.0
      },
      {
        "itemID": 239656,
        "name": "Adherent's Silken Shroud",
        "icon": "inv_cape_cloth_questbloodelf_b_01",
        "count": 3,
        "pct": 11.5,
        "avg_itemLevel": 285.0
      },
      {
        "itemID": 258575,
        "name": "Rigid Scale Greatcloak",
        "icon": "inv_cape_draenordungeon_c_02_plate",
        "count": 2,
        "pct": 7.7,
        "avg_itemLevel": 289.0
      },
      {
        "itemID": 249370,
        "name": "Draconic Nullcape",
        "icon": "inv_plate_revendrethraid_d_01_cape",
        "count": 1,
        "pct": 3.8,
        "avg_itemLevel": 289.0
      }
    ],
    "back": [
      {
        "itemID": 239656,
        "name": "Adherent's Silken Shroud",
        "icon": "inv_cape_cloth_questbloodelf_b_01",
        "count": 14,
        "pct": 53.8,
        "avg_itemLevel": 285.0
      },
      {
        "itemID": 249280,
        "name": "Emblazoned Sunglaive",
        "icon": "inv_glaive_1h_raidmidnight_d_01",
        "count": 5,
        "pct": 19.2,
        "avg_itemLevel": 298.0
      },
      {
        "itemID": 250028,
        "name": "Devouring Reaver's Drape",
        "icon": "inv_cape_leather_raiddemonhuntermidnight_d_01",
        "count": 2,
        "pct": 7.7,
        "avg_itemLevel": 289.0
      },
      {
        "itemID": 251175,
        "name": "Soulblight Cleaver",
        "icon": "inv_axe_1h_amani_b_01",
        "count": 2,
        "pct": 7.7,
        "avg_itemLevel": 298.0
      },
      {
        "itemID": 260408,
        "name": "Lightless Lament",
        "icon": "inv_glaive_1h_darknaaru_d_01",
        "count": 1,
        "pct": 3.8,
        "avg_itemLevel": 298.0
      },
      {
        "itemID": 249370,
        "name": "Draconic Nullcape",
        "icon": "inv_plate_revendrethraid_d_01_cape",
        "count": 1,
        "pct": 3.8,
        "avg_itemLevel": 289.0
      },
      {
        "itemID": 237840,
        "name": "Spellbreaker's Warglaive",
        "icon": "inv_glaive_1h_questbloodelf_b_01",
        "count": 1,
        "pct": 3.8,
        "avg_itemLevel": 295.0
      }
    ],
    "main_hand": [
      {
        "itemID": 249280,
        "name": "Emblazoned Sunglaive",
        "icon": "inv_glaive_1h_raidmidnight_d_01",
        "count": 10,
        "pct": 38.5,
        "avg_itemLevel": 296.1
      },
      {
        "itemID": 260408,
        "name": "Lightless Lament",
        "icon": "inv_glaive_1h_darknaaru_d_01",
        "count": 5,
        "pct": 19.2,
        "avg_itemLevel": 298.0
      },
      {
        "itemID": 237840,
        "name": "Spellbreaker's Warglaive",
        "icon": "inv_glaive_1h_questbloodelf_b_01",
        "count": 3,
        "pct": 11.5,
        "avg_itemLevel": 295.0
      },
      {
        "itemID": 251175,
        "name": "Soulblight Cleaver",
        "icon": "inv_axe_1h_amani_b_01",
        "count": 3,
        "pct": 11.5,
        "avg_itemLevel": 298.0
      },
      {
        "itemID": 258438,
        "name": "Blazing Sunclaws",
        "icon": "inv_hand_1h_draenordungeon_c_01",
        "count": 1,
        "pct": 3.8,
        "avg_itemLevel": 298.0
      },
      {
        "itemID": 237850,
        "name": "Farstrider's Chopper",
        "icon": "inv_axe_1h_questbloodelf_b_01",
        "count": 1,
        "pct": 3.8,
        "avg_itemLevel": 295.0
      },
      {
        "itemID": 260423,
        "name": "Arator's Swift Remembrance",
        "icon": "inv_sword_1h_raidmidnight_d_01",
        "count": 1,
        "pct": 3.8,
        "avg_itemLevel": 289.0
      },
      {
        "itemID": 251122,
        "name": "Shadowslash Slicer",
        "icon": "inv_sword_1h_domanaar_b_01",
        "count": 1,
        "pct": 3.8,
        "avg_itemLevel": 298.0
      },
      {
        "itemID": 193717,
        "name": "Mystakria's Harvester",
        "icon": "inv_glaive_1h_drakonid_c_01",
        "count": 1,
        "pct": 3.8,
        "avg_itemLevel": 298.0
      }
    ],
    "off_hand": [
      {
        "itemID": 249280,
        "name": "Emblazoned Sunglaive",
        "icon": "inv_glaive_1h_raidmidnight_d_01",
        "count": 7,
        "pct": 26.9,
        "avg_itemLevel": 296.7
      },
      {
        "itemID": 260408,
        "name": "Lightless Lament",
        "icon": "inv_glaive_1h_darknaaru_d_01",
        "count": 3,
        "pct": 11.5,
        "avg_itemLevel": 298.0
      },
      {
        "itemID": 237840,
        "name": "Spellbreaker's Warglaive",
        "icon": "inv_glaive_1h_questbloodelf_b_01",
        "count": 3,
        "pct": 11.5,
        "avg_itemLevel": 295.0
      },
      {
        "itemID": 260423,
        "name": "Arator's Swift Remembrance",
        "icon": "inv_sword_1h_raidmidnight_d_01",
        "count": 1,
        "pct": 3.8,
        "avg_itemLevel": 298.0
      },
      {
        "itemID": 157758,
        "name": "Ren'dorei Tabard",
        "icon": "inv_tabard_a_97voidelf",
        "count": 1,
        "pct": 3.8,
        "avg_itemLevel": 1.0
      },
      {
        "itemID": 258438,
        "name": "Blazing Sunclaws",
        "icon": "inv_hand_1h_draenordungeon_c_01",
        "count": 1,
        "pct": 3.8,
        "avg_itemLevel": 298.0
      },
      {
        "itemID": 251106,
        "name": "Resolute Runeglaive",
        "icon": "inv_glaive_1h_bloodelfguard_d_01",
        "count": 1,
        "pct": 3.8,
        "avg_itemLevel": 272.0
      },
      {
        "itemID": 69210,
        "name": "Renowned Guild Tabard",
        "icon": "inv_epicguildtabard",
        "count": 1,
        "pct": 3.8,
        "avg_itemLevel": 1.0
      },
      {
        "itemID": 193717,
        "name": "Mystakria's Harvester",
        "icon": "inv_glaive_1h_drakonid_c_01",
        "count": 1,
        "pct": 3.8,
        "avg_itemLevel": 298.0
      }
    ],
    "tabard": [
      {
        "itemID": 233290,
        "name": "Sacred Templar's Tabard",
        "icon": "inv_tabard_nightfall_c_01",
        "count": 2,
        "pct": 7.7,
        "avg_itemLevel": 1.0
      },
      {
        "itemID": 69210,
        "name": "Renowned Guild Tabard",
        "icon": "inv_epicguildtabard",
        "count": 1,
        "pct": 3.8,
        "avg_itemLevel": 1.0
      },
      {
        "itemID": 198730,
        "name": "Dragonscale Expedition Tabard",
        "icon": "inv_tabard_dragonscaleexpedition_c_01",
        "count": 1,
        "pct": 3.8,
        "avg_itemLevel": 1.0
      },
      {
        "itemID": 149451,
        "name": "Demonic Gladiator's Tabard",
        "icon": "inv_tabard_legionpvps4_alliance",
        "count": 1,
        "pct": 3.8,
        "avg_itemLevel": 15.0
      },
      {
        "itemID": 38312,
        "name": "Tabard of Brilliance",
        "icon": "inv_shirt_guildtabard_01",
        "count": 1,
        "pct": 3.8,
        "avg_itemLevel": 1.0
      },
      {
        "itemID": 69209,
        "name": "Illustrious Guild Tabard",
        "icon": "inv_rareguildtabard",
        "count": 1,
        "pct": 3.8,
        "avg_itemLevel": 1.0
      },
      {
        "itemID": 160544,
        "name": "Champions of Azeroth Tabard",
        "icon": "inv_tabard_championsofazeroth",
        "count": 1,
        "pct": 3.8,
        "avg_itemLevel": 15.0
      },
      {
        "itemID": 23705,
        "name": "Tabard of Flame",
        "icon": "inv_misc_tabardpvp_02",
        "count": 1,
        "pct": 3.8,
        "avg_itemLevel": 1.0
      },
      {
        "itemID": 216667,
        "name": "Draconic Gladiator's Tabard",
        "icon": "inv_tabard_pvp_10season4_d_01",
        "count": 1,
        "pct": 3.8,
        "avg_itemLevel": 1.0
      },
      {
        "itemID": 233288,
        "name": "Radiant Recruit's Tabard",
        "icon": "inv_tabard_nightfall_a_01",
        "count": 1,
        "pct": 3.8,
        "avg_itemLevel": 1.0
      }
    ]
  },
  "race": {},
  "factions": {
    "alliance": 24,
    "horde": 2
  },
  "guilds": [
    {
      "name": "Copium",
      "count": 1
    },
    {
      "name": "No Skill",
      "count": 1
    },
    {
      "name": "Энивей",
      "count": 1
    },
    {
      "name": "Shade",
      "count": 1
    },
    {
      "name": "Infinity",
      "count": 1
    },
    {
      "name": "grr woof woof bark",
      "count": 1
    },
    {
      "name": "Denial of Service",
      "count": 1
    },
    {
      "name": "Retreat",
      "count": 1
    },
    {
      "name": "Salt Mines",
      "count": 1
    },
    {
      "name": "Resonate",
      "count": 1
    },
    {
      "name": "Лё Резистанс",
      "count": 1
    },
    {
      "name": "Vestige",
      "count": 1
    },
    {
      "name": "Soft Enrage",
      "count": 1
    },
    {
      "name": "Strange Behaviour",
      "count": 1
    },
    {
      "name": "Unexpected",
      "count": 1
    }
  ],
  "kill_time": {
    "avg": 380606.3,
    "median": 390395.0,
    "p25": 353860.0,
    "p75": 404816.0
  },
  "stats": {},
  "gems": []
}